[{"key":"30063","brand_id":"94","series_id":"951","value":"2016\u6b3e 1.5T COOPER CABRIO","nameL":"2016\u6b3e MINI 1.5T COOPER CABRIO","price":"32.5","year":"2016","max_year":"2016","min_year":"2016"},{"key":"30064","brand_id":"94","series_id":"951","value":"2016\u6b3e 1.5T COOPER CABRIO \u52a0\u52d2\u6bd4\u84dd\u9650\u91cf\u7248","nameL":"2016\u6b3e MINI 1.5T COOPER CABRIO \u52a0\u52d2\u6bd4\u84dd\u9650\u91cf\u7248","price":"34","year":"2016","max_year":"2016","min_year":"2016"},{"key":"30065","brand_id":"94","series_id":"951","value":"2016\u6b3e 2.0T COOPER S CABRIO","nameL":"2016\u6b3e MINI 2.0T COOPER S CABRIO","price":"37.5","year":"2016","max_year":"2016","min_year":"2016"},{"key":"30066","brand_id":"94","series_id":"951","value":"2016\u6b3e 2.0T COOPER S CABRIO \u52a0\u52d2\u6bd4\u84dd\u9650\u91cf\u7248","nameL":"2016\u6b3e MINI 2.0T COOPER S CABRIO \u52a0\u52d2\u6bd4\u84dd\u9650\u91cf\u7248","price":"38.5","year":"2016","max_year":"2016","min_year":"2016"},{"key":"26185","brand_id":"94","series_id":"951","value":"2015\u6b3e 1.2T \u624b\u52a8 ONE","nameL":"2015\u6b3e MINI 1.2T \u624b\u52a8 ONE","price":"18.5","year":"2015","max_year":"2016","min_year":"2015"},{"key":"23494","brand_id":"94","series_id":"951","value":"2015\u6b3e 1.2T ONE \u624b\u52a8","nameL":"2015\u6b3e MINI 1.2T ONE \u624b\u52a8","price":"18.5","year":"2015","max_year":"2016","min_year":"2014"},{"key":"26186","brand_id":"94","series_id":"951","value":"2015\u6b3e 1.2T \u624b\u52a8 ONE \u4e94\u95e8\u7248","nameL":"2015\u6b3e MINI 1.2T \u624b\u52a8 ONE \u4e94\u95e8\u7248","price":"19.5","year":"2015","max_year":"2016","min_year":"2014"},{"key":"26187","brand_id":"94","series_id":"951","value":"2015\u6b3e 1.2T ONE \u4e94\u95e8\u7248","nameL":"2015\u6b3e MINI 1.2T ONE \u4e94\u95e8\u7248","price":"21.9","year":"2015","max_year":"2016","min_year":"2014"},{"key":"26188","brand_id":"94","series_id":"951","value":"2015\u6b3e 1.5T COOPER Fun \u4e94\u95e8\u7248","nameL":"2015\u6b3e MINI 1.5T COOPER Fun \u4e94\u95e8\u7248","price":"26.9","year":"2015","max_year":"2016","min_year":"2014"},{"key":"26189","brand_id":"94","series_id":"951","value":"2015\u6b3e 1.5T COOPER Excitement \u4e94\u95e8\u7248","nameL":"2015\u6b3e MINI 1.5T COOPER Excitement \u4e94\u95e8\u7248","price":"29.9","year":"2015","max_year":"2016","min_year":"2014"},{"key":"23495","brand_id":"94","series_id":"951","value":"2015\u6b3e 2.0T COOPER S \u624b\u52a8","nameL":"2015\u6b3e MINI 2.0T COOPER S \u624b\u52a8","price":"28.5","year":"2015","max_year":"2016","min_year":"2014"},{"key":"26190","brand_id":"94","series_id":"951","value":"2015\u6b3e 2.0T COOPER S \u4e94\u95e8\u7248","nameL":"2015\u6b3e MINI 2.0T COOPER S \u4e94\u95e8\u7248","price":"33.9","year":"2015","max_year":"2016","min_year":"2014"},{"key":"22425","brand_id":"94","series_id":"951","value":"2014\u6b3e 1.2T ONE","nameL":"2014\u6b3e MINI 1.2T ONE","price":"20.5","year":"2014","max_year":"2016","min_year":"2014"},{"key":"22426","brand_id":"94","series_id":"951","value":"2014\u6b3e 1.2T ONE+","nameL":"2014\u6b3e MINI 1.2T ONE+","price":"22.5","year":"2014","max_year":"2016","min_year":"2014"},{"key":"22427","brand_id":"94","series_id":"951","value":"2014\u6b3e 1.5T COOPER Fun","nameL":"2014\u6b3e MINI 1.5T COOPER Fun","price":"25.5","year":"2014","max_year":"2016","min_year":"2014"},{"key":"22428","brand_id":"94","series_id":"951","value":"2014\u6b3e 1.5T COOPER Excitement","nameL":"2014\u6b3e MINI 1.5T COOPER Excitement","price":"28.5","year":"2014","max_year":"2016","min_year":"2014"},{"key":"22429","brand_id":"94","series_id":"951","value":"2014\u6b3e 2.0T COOPER S Fun","nameL":"2014\u6b3e MINI 2.0T COOPER S Fun","price":"30.5","year":"2014","max_year":"2016","min_year":"2014"},{"key":"22430","brand_id":"94","series_id":"951","value":"2014\u6b3e 2.0T COOPER S Excitement","nameL":"2014\u6b3e MINI 2.0T COOPER S Excitement","price":"33.5","year":"2014","max_year":"2016","min_year":"2014"},{"key":"13700","brand_id":"94","series_id":"951","value":"2013\u6b3e ONE \u9650\u91cf\u7248\u7b2c\u4e09\u6b3e","nameL":"2013\u6b3e MINI ONE \u9650\u91cf\u7248\u7b2c\u4e09\u6b3e","price":"23.7","year":"2013","max_year":"2015","min_year":"2013"},{"key":"13701","brand_id":"94","series_id":"951","value":"2013\u6b3e ONE \u9650\u91cf\u7248\u7b2c\u4e00\u6b3e","nameL":"2013\u6b3e MINI ONE \u9650\u91cf\u7248\u7b2c\u4e00\u6b3e","price":"23.7","year":"2013","max_year":"2015","min_year":"2013"},{"key":"13702","brand_id":"94","series_id":"951","value":"2013\u6b3e ONE \u9650\u91cf\u7248\u7b2c\u4e8c\u6b3e","nameL":"2013\u6b3e MINI ONE \u9650\u91cf\u7248\u7b2c\u4e8c\u6b3e","price":"23.7","year":"2013","max_year":"2015","min_year":"2013"},{"key":"13707","brand_id":"94","series_id":"951","value":"2012\u6b3e COOPER S Fun","nameL":"2012\u6b3e MINI COOPER S Fun","price":"31.9","year":"2012","max_year":"2014","min_year":"2012"},{"key":"20965","brand_id":"94","series_id":"951","value":"2012\u6b3e 1.6T COOPER S \u4e2d\u56fd\u4efb\u52a1\u7248","nameL":"2012\u6b3e MINI 1.6T COOPER S \u4e2d\u56fd\u4efb\u52a1\u7248","price":"34.7","year":"2012","max_year":"2014","min_year":"2012"},{"key":"13709","brand_id":"94","series_id":"951","value":"2012\u6b3e COOPER S Bayswater","nameL":"2012\u6b3e MINI COOPER S Bayswater","price":"36.9","year":"2012","max_year":"2014","min_year":"2012"},{"key":"13710","brand_id":"94","series_id":"951","value":"2012\u6b3e COOPER S \u655e\u7bf7 Highgate","nameL":"2012\u6b3e MINI COOPER S \u655e\u7bf7 Highgate","price":"41.9","year":"2012","max_year":"2014","min_year":"2012"},{"key":"13711","brand_id":"94","series_id":"951","value":"2012\u6b3e GOODWOOD","nameL":"2012\u6b3e MINI GOODWOOD","price":"52.2","year":"2012","max_year":"2014","min_year":"2012"},{"key":"13703","brand_id":"94","series_id":"951","value":"2012\u6b3e ONE Baker Street","nameL":"2012\u6b3e MINI ONE Baker Street","price":"24.5","year":"2012","max_year":"2014","min_year":"2012"},{"key":"13704","brand_id":"94","series_id":"951","value":"2012\u6b3e COOPER Baker Street","nameL":"2012\u6b3e MINI COOPER Baker Street","price":"27.8","year":"2012","max_year":"2014","min_year":"2012"},{"key":"13705","brand_id":"94","series_id":"951","value":"2012\u6b3e 1.6L \u4e2d\u56fd\u5965\u6797\u5339\u514b\u7eaa\u5ff5\u7248","nameL":"2012\u6b3e MINI 1.6L \u4e2d\u56fd\u5965\u6797\u5339\u514b\u7eaa\u5ff5\u7248","price":"29.6","year":"2012","max_year":"2014","min_year":"2012"},{"key":"13706","brand_id":"94","series_id":"951","value":"2012\u6b3e COOPER Bayswater","nameL":"2012\u6b3e MINI COOPER Bayswater","price":"31.6","year":"2012","max_year":"2014","min_year":"2012"},{"key":"13708","brand_id":"94","series_id":"951","value":"2012\u6b3e COOPER \u655e\u7bf7 Highgate","nameL":"2012\u6b3e MINI COOPER \u655e\u7bf7 Highgate","price":"36.9","year":"2012","max_year":"2014","min_year":"2012"},{"key":"13724","brand_id":"94","series_id":"951","value":"2011\u6b3e COOPER S","nameL":"2011\u6b3e MINI COOPER S","price":"35.9","year":"2011","max_year":"2013","min_year":"2010"},{"key":"20964","brand_id":"94","series_id":"951","value":"2011\u6b3e 1.6T COOPER S CABRIO","nameL":"2011\u6b3e MINI 1.6T COOPER S CABRIO","price":"41.5","year":"2011","max_year":"2013","min_year":"2010"},{"key":"13721","brand_id":"94","series_id":"951","value":"2011\u6b3e ONE","nameL":"2011\u6b3e MINI ONE","price":"22.5","year":"2011","max_year":"2013","min_year":"2010"},{"key":"13722","brand_id":"94","series_id":"951","value":"2011\u6b3e COOPER Fun","nameL":"2011\u6b3e MINI COOPER Fun","price":"26.9","year":"2011","max_year":"2013","min_year":"2010"},{"key":"20962","brand_id":"94","series_id":"951","value":"2011\u6b3e 1.6L COOPER Tattoo","nameL":"2011\u6b3e MINI 1.6L COOPER Tattoo","price":"28.7","year":"2011","max_year":"2013","min_year":"2011"},{"key":"13723","brand_id":"94","series_id":"951","value":"2011\u6b3e COOPER Excitement","nameL":"2011\u6b3e MINI COOPER Excitement","price":"30.9","year":"2011","max_year":"2013","min_year":"2010"},{"key":"20963","brand_id":"94","series_id":"951","value":"2011\u6b3e 1.6L COOPER CABRIO","nameL":"2011\u6b3e MINI 1.6L COOPER CABRIO","price":"35.5","year":"2011","max_year":"2013","min_year":"2010"},{"key":"13716","brand_id":"94","series_id":"951","value":"2010\u6b3e 1.6T COOPER S 50 Camden","nameL":"2010\u6b3e MINI 1.6T COOPER S 50 Camden","price":"37.9","year":"2010","max_year":"2012","min_year":"2009"},{"key":"13713","brand_id":"94","series_id":"951","value":"2010\u6b3e 1.6 COPPER Cheer","nameL":"2010\u6b3e MINI 1.6 COPPER Cheer","price":"24.9","year":"2010","max_year":"2012","min_year":"2009"},{"key":"13714","brand_id":"94","series_id":"951","value":"2010\u6b3e 1.6 COOPER Fun","nameL":"2010\u6b3e MINI 1.6 COOPER Fun","price":"26.9","year":"2010","max_year":"2012","min_year":"2009"},{"key":"13715","brand_id":"94","series_id":"951","value":"2010\u6b3e 1.6 COPPER Mayfair","nameL":"2010\u6b3e MINI 1.6 COPPER Mayfair","price":"33.9","year":"2010","max_year":"2012","min_year":"2009"},{"key":"28965","brand_id":"94","series_id":"951","value":"2009\u6b3e 1.6T COOPER S CABRIO","nameL":"2009\u6b3e MINI 1.6T COOPER S CABRIO","price":"42.95","year":"2009","max_year":"2011","min_year":"2008"},{"key":"28966","brand_id":"94","series_id":"951","value":"2009\u6b3e 1.6L COOPER CABRIO","nameL":"2009\u6b3e MINI 1.6L COOPER CABRIO","price":"36.95","year":"2009","max_year":"2011","min_year":"2008"},{"key":"13717","brand_id":"94","series_id":"951","value":"2008\u6b3e 1.6T COOPER S","nameL":"2008\u6b3e MINI 1.6T COOPER S","price":"36.5","year":"2008","max_year":"2011","min_year":"2007"},{"key":"13718","brand_id":"94","series_id":"951","value":"2007\u6b3e 1.6L COOPER Fun","nameL":"2007\u6b3e MINI 1.6L COOPER Fun","price":"28","year":"2007","max_year":"2011","min_year":"2006"},{"key":"13719","brand_id":"94","series_id":"951","value":"2007\u6b3e 1.6L COOPER Excitement","nameL":"2007\u6b3e MINI 1.6L COOPER Excitement","price":"31.8","year":"2007","max_year":"2011","min_year":"2007"},{"key":"28967","brand_id":"94","series_id":"951","value":"2006\u6b3e 1.6T COOPER S Gp","nameL":"2006\u6b3e MINI 1.6T COOPER S Gp","price":"75","year":"2006","max_year":"2010","min_year":"2005"},{"key":"28968","brand_id":"94","series_id":"951","value":"2006\u6b3e 1.6 Seven","nameL":"2006\u6b3e MINI 1.6 Seven","price":"32.8","year":"2006","max_year":"2010","min_year":"2005"},{"key":"28969","brand_id":"94","series_id":"951","value":"2006\u6b3e 1.6 Park Lane","nameL":"2006\u6b3e MINI 1.6 Park Lane","price":"32.8","year":"2006","max_year":"2010","min_year":"2005"},{"key":"28970","brand_id":"94","series_id":"951","value":"2006\u6b3e 1.6 Checkmate","nameL":"2006\u6b3e MINI 1.6 Checkmate","price":"32.8","year":"2006","max_year":"2010","min_year":"2005"},{"key":"13720","brand_id":"94","series_id":"951","value":"2004\u6b3e 1.6 Cooper","nameL":"2004\u6b3e MINI 1.6 Cooper","price":"32.8","year":"2004","max_year":"2007","min_year":"2004"},{"key":"28971","brand_id":"94","series_id":"951","value":"2004\u6b3e 1.6 COOPER CABRIO","nameL":"2004\u6b3e MINI 1.6 COOPER CABRIO","price":"39.5","year":"2004","max_year":"2007","min_year":"2003"}]