[{"key":"13819","brand_id":"99","series_id":"979","value":"2007\u6b3e \u5947\u9a8f TM6501\u7cfb\u5217\u7ecf\u6d4e\u578b","nameL":"2007\u6b3e \u5947\u9a8f TM6501\u7cfb\u5217\u7ecf\u6d4e\u578b","price":"6.38","year":"2007","max_year":"2011","min_year":"2007"},{"key":"13820","brand_id":"99","series_id":"979","value":"2007\u6b3e \u5947\u9a8f TM6501\u7cfb\u5217\u6807\u51c6\u578b","nameL":"2007\u6b3e \u5947\u9a8f TM6501\u7cfb\u5217\u6807\u51c6\u578b","price":"6.6","year":"2007","max_year":"2011","min_year":"2006"}]