[{"key":"9080","brand_id":"55","series_id":"626","value":"2006\u6b3e DD6471B","nameL":"2006\u6b3e \u50b2\u7f9a DD6471B","price":"8.88","year":"2006","max_year":"2010","min_year":"2005"},{"key":"9083","brand_id":"55","series_id":"626","value":"2005\u6b3e DD6490D","nameL":"2005\u6b3e \u50b2\u7f9a DD6490D","price":"12.98","year":"2005","max_year":"2009","min_year":"2004"},{"key":"9084","brand_id":"55","series_id":"626","value":"2004\u6b3e DD6490C","nameL":"2004\u6b3e \u50b2\u7f9a DD6490C","price":"11.88","year":"2004","max_year":"2008","min_year":"2003"},{"key":"9085","brand_id":"55","series_id":"626","value":"2003\u6b3e DG6471B","nameL":"2003\u6b3e \u50b2\u7f9a DG6471B","price":"8.88","year":"2003","max_year":"2007","min_year":"2002"}]