[{"key":"29449","brand_id":"7","series_id":"103","value":"2016\u6b3e 640i Gran Coupe","nameL":"2016\u6b3e \u5b9d\u9a6c6\u7cfb 640i Gran Coupe","price":"95.2","year":"2016","max_year":"2016","min_year":"2015"},{"key":"29450","brand_id":"7","series_id":"103","value":"2016\u6b3e 640i xDrive Gran Coupe","nameL":"2016\u6b3e \u5b9d\u9a6c6\u7cfb 640i xDrive Gran Coupe","price":"98.2","year":"2016","max_year":"2016","min_year":"2015"},{"key":"29451","brand_id":"7","series_id":"103","value":"2016\u6b3e 640i\u53cc\u95e8\u8f7f\u8dd1\u8f66","nameL":"2016\u6b3e \u5b9d\u9a6c6\u7cfb 640i\u53cc\u95e8\u8f7f\u8dd1\u8f66","price":"106.8","year":"2016","max_year":"2016","min_year":"2015"},{"key":"29452","brand_id":"7","series_id":"103","value":"2016\u6b3e 640i xDrive\u53cc\u95e8\u8f7f\u8dd1\u8f66","nameL":"2016\u6b3e \u5b9d\u9a6c6\u7cfb 640i xDrive\u53cc\u95e8\u8f7f\u8dd1\u8f66","price":"109.8","year":"2016","max_year":"2016","min_year":"2015"},{"key":"29453","brand_id":"7","series_id":"103","value":"2016\u6b3e 640i\u655e\u7bf7\u8f7f\u8dd1\u8f66","nameL":"2016\u6b3e \u5b9d\u9a6c6\u7cfb 640i\u655e\u7bf7\u8f7f\u8dd1\u8f66","price":"112.8","year":"2016","max_year":"2016","min_year":"2015"},{"key":"29454","brand_id":"7","series_id":"103","value":"2016\u6b3e 640i xDrive\u655e\u7bf7\u8f7f\u8dd1\u8f66","nameL":"2016\u6b3e \u5b9d\u9a6c6\u7cfb 640i xDrive\u655e\u7bf7\u8f7f\u8dd1\u8f66","price":"115.8","year":"2016","max_year":"2016","min_year":"2015"},{"key":"29455","brand_id":"7","series_id":"103","value":"2016\u6b3e 650i xDrive Gran Coupe","nameL":"2016\u6b3e \u5b9d\u9a6c6\u7cfb 650i xDrive Gran Coupe","price":"164.8","year":"2016","max_year":"2016","min_year":"2015"},{"key":"29456","brand_id":"7","series_id":"103","value":"2016\u6b3e 650i xDrive\u53cc\u95e8\u8f7f\u8dd1\u8f66","nameL":"2016\u6b3e \u5b9d\u9a6c6\u7cfb 650i xDrive\u53cc\u95e8\u8f7f\u8dd1\u8f66","price":"179.2","year":"2016","max_year":"2016","min_year":"2015"},{"key":"29457","brand_id":"7","series_id":"103","value":"2016\u6b3e 650i xDrive\u655e\u7bf7\u8f7f\u8dd1\u8f66","nameL":"2016\u6b3e \u5b9d\u9a6c6\u7cfb 650i xDrive\u655e\u7bf7\u8f7f\u8dd1\u8f66","price":"188.2","year":"2016","max_year":"2016","min_year":"2015"},{"key":"1556","brand_id":"7","series_id":"103","value":"2013\u6b3e 640i \u53cc\u95e8\u8f7f\u8dd1\u8f66","nameL":"2013\u6b3e \u5b9d\u9a6c6\u7cfb 640i \u53cc\u95e8\u8f7f\u8dd1\u8f66","price":"112.8","year":"2013","max_year":"2016","min_year":"2012"},{"key":"20427","brand_id":"7","series_id":"103","value":"2013\u6b3e \u6539\u6b3e 640i\u53cc\u95e8\u8f7f\u8dd1\u8f66","nameL":"2013\u6b3e \u5b9d\u9a6c6\u7cfb \u6539\u6b3e 640i\u53cc\u95e8\u8f7f\u8dd1\u8f66","price":"113.9","year":"2013","max_year":"2016","min_year":"2013"},{"key":"1558","brand_id":"7","series_id":"103","value":"2013\u6b3e 640i xDrive\u53cc\u95e8\u8f7f\u8dd1\u8f66","nameL":"2013\u6b3e \u5b9d\u9a6c6\u7cfb 640i xDrive\u53cc\u95e8\u8f7f\u8dd1\u8f66","price":"116.9","year":"2013","max_year":"2016","min_year":"2013"},{"key":"1559","brand_id":"7","series_id":"103","value":"2013\u6b3e 640i \u655e\u7bf7\u8f7f\u8dd1\u8f66","nameL":"2013\u6b3e \u5b9d\u9a6c6\u7cfb 640i \u655e\u7bf7\u8f7f\u8dd1\u8f66","price":"119.8","year":"2013","max_year":"2016","min_year":"2012"},{"key":"20428","brand_id":"7","series_id":"103","value":"2013\u6b3e \u6539\u6b3e 640i\u655e\u7bf7\u8f7f\u8dd1\u8f66","nameL":"2013\u6b3e \u5b9d\u9a6c6\u7cfb \u6539\u6b3e 640i\u655e\u7bf7\u8f7f\u8dd1\u8f66","price":"119.8","year":"2013","max_year":"2016","min_year":"2013"},{"key":"1561","brand_id":"7","series_id":"103","value":"2013\u6b3e 640i Gran Coupe","nameL":"2013\u6b3e \u5b9d\u9a6c6\u7cfb 640i Gran Coupe","price":"121.8","year":"2013","max_year":"2016","min_year":"2013"},{"key":"1562","brand_id":"7","series_id":"103","value":"2013\u6b3e 640i xDrive \u655e\u7bf7\u8f7f\u8dd1\u8f66","nameL":"2013\u6b3e \u5b9d\u9a6c6\u7cfb 640i xDrive \u655e\u7bf7\u8f7f\u8dd1\u8f66","price":"122.8","year":"2013","max_year":"2016","min_year":"2013"},{"key":"1563","brand_id":"7","series_id":"103","value":"2013\u6b3e 640i xDrive Gran Coupe","nameL":"2013\u6b3e \u5b9d\u9a6c6\u7cfb 640i xDrive Gran Coupe","price":"125.8","year":"2013","max_year":"2016","min_year":"2013"},{"key":"1564","brand_id":"7","series_id":"103","value":"2013\u6b3e 650i xDrive \u53cc\u95e8\u8f7f\u8dd1\u8f66","nameL":"2013\u6b3e \u5b9d\u9a6c6\u7cfb 650i xDrive \u53cc\u95e8\u8f7f\u8dd1\u8f66","price":"188.9","year":"2013","max_year":"2016","min_year":"2012"},{"key":"20429","brand_id":"7","series_id":"103","value":"2013\u6b3e \u6539\u6b3e 650i xDrive\u53cc\u95e8\u8f7f\u8dd1\u8f66","nameL":"2013\u6b3e \u5b9d\u9a6c6\u7cfb \u6539\u6b3e 650i xDrive\u53cc\u95e8\u8f7f\u8dd1\u8f66","price":"188.9","year":"2013","max_year":"2016","min_year":"2013"},{"key":"1565","brand_id":"7","series_id":"103","value":"2013\u6b3e 650i xDrive \u655e\u7bf7\u8f7f\u8dd1\u8f66","nameL":"2013\u6b3e \u5b9d\u9a6c6\u7cfb 650i xDrive \u655e\u7bf7\u8f7f\u8dd1\u8f66","price":"198.3","year":"2013","max_year":"2016","min_year":"2012"},{"key":"20430","brand_id":"7","series_id":"103","value":"2013\u6b3e \u6539\u6b3e 650i xDrive\u655e\u7bf7\u8f7f\u8dd1\u8f66","nameL":"2013\u6b3e \u5b9d\u9a6c6\u7cfb \u6539\u6b3e 650i xDrive\u655e\u7bf7\u8f7f\u8dd1\u8f66","price":"198.3","year":"2013","max_year":"2016","min_year":"2013"},{"key":"1566","brand_id":"7","series_id":"103","value":"2013\u6b3e 650i xDrive Gran Coupe","nameL":"2013\u6b3e \u5b9d\u9a6c6\u7cfb 650i xDrive Gran Coupe","price":"201.8","year":"2013","max_year":"2016","min_year":"2012"},{"key":"1567","brand_id":"7","series_id":"103","value":"2012\u6b3e 640i \u53cc\u95e8\u8f7f\u8dd1\u8f66","nameL":"2012\u6b3e \u5b9d\u9a6c6\u7cfb 640i \u53cc\u95e8\u8f7f\u8dd1\u8f66","price":"112.8","year":"2012","max_year":"2014","min_year":"2011"},{"key":"1568","brand_id":"7","series_id":"103","value":"2012\u6b3e 640i Gran Coupe","nameL":"2012\u6b3e \u5b9d\u9a6c6\u7cfb 640i Gran Coupe","price":"120.5","year":"2012","max_year":"2014","min_year":"2012"},{"key":"1569","brand_id":"7","series_id":"103","value":"2012\u6b3e 650i \u53cc\u95e8\u8f7f\u8dd1\u8f66","nameL":"2012\u6b3e \u5b9d\u9a6c6\u7cfb 650i \u53cc\u95e8\u8f7f\u8dd1\u8f66","price":"193.7","year":"2012","max_year":"2014","min_year":"2011"},{"key":"1570","brand_id":"7","series_id":"103","value":"2012\u6b3e 650i xDrive Gran Coupe","nameL":"2012\u6b3e \u5b9d\u9a6c6\u7cfb 650i xDrive Gran Coupe","price":"200.5","year":"2012","max_year":"2014","min_year":"2011"},{"key":"1571","brand_id":"7","series_id":"103","value":"2011\u6b3e 640i \u53cc\u95e8\u8f7f\u8dd1\u8f66","nameL":"2011\u6b3e \u5b9d\u9a6c6\u7cfb 640i \u53cc\u95e8\u8f7f\u8dd1\u8f66","price":"112.8","year":"2011","max_year":"2013","min_year":"2011"},{"key":"1572","brand_id":"7","series_id":"103","value":"2011\u6b3e 640i \u655e\u7bf7\u8f7f\u8dd1","nameL":"2011\u6b3e \u5b9d\u9a6c6\u7cfb 640i \u655e\u7bf7\u8f7f\u8dd1","price":"118.6","year":"2011","max_year":"2013","min_year":"2011"},{"key":"1573","brand_id":"7","series_id":"103","value":"2011\u6b3e 650i \u53cc\u95e8\u8f7f\u8dd1\u8f66","nameL":"2011\u6b3e \u5b9d\u9a6c6\u7cfb 650i \u53cc\u95e8\u8f7f\u8dd1\u8f66","price":"193.7","year":"2011","max_year":"2013","min_year":"2011"},{"key":"1574","brand_id":"7","series_id":"103","value":"2011\u6b3e 650i \u655e\u7bf7\u8f7f\u8dd1","nameL":"2011\u6b3e \u5b9d\u9a6c6\u7cfb 650i \u655e\u7bf7\u8f7f\u8dd1","price":"203.9","year":"2011","max_year":"2013","min_year":"2011"},{"key":"1575","brand_id":"7","series_id":"103","value":"2008\u6b3e 630Ci\u786c\u9876","nameL":"2008\u6b3e \u5b9d\u9a6c6\u7cfb 630Ci\u786c\u9876","price":"106.9","year":"2008","max_year":"2012","min_year":"2007"},{"key":"1576","brand_id":"7","series_id":"103","value":"2007\u6b3e 630i \u53cc\u95e8\u8f7f\u8dd1\u8f66","nameL":"2007\u6b3e \u5b9d\u9a6c6\u7cfb 630i \u53cc\u95e8\u8f7f\u8dd1\u8f66","price":"108.2","year":"2007","max_year":"2011","min_year":"2007"},{"key":"1577","brand_id":"7","series_id":"103","value":"2007\u6b3e 630i \u655e\u7bf7\u8f7f\u8dd1\u8f66","nameL":"2007\u6b3e \u5b9d\u9a6c6\u7cfb 630i \u655e\u7bf7\u8f7f\u8dd1\u8f66","price":"113.5","year":"2007","max_year":"2011","min_year":"2007"},{"key":"1578","brand_id":"7","series_id":"103","value":"2007\u6b3e 650i \u53cc\u95e8\u8f7f\u8dd1\u8f66","nameL":"2007\u6b3e \u5b9d\u9a6c6\u7cfb 650i \u53cc\u95e8\u8f7f\u8dd1\u8f66","price":"184.8","year":"2007","max_year":"2011","min_year":"2007"},{"key":"1579","brand_id":"7","series_id":"103","value":"2007\u6b3e 650i \u655e\u7bf7\u8f7f\u8dd1\u8f66","nameL":"2007\u6b3e \u5b9d\u9a6c6\u7cfb 650i \u655e\u7bf7\u8f7f\u8dd1\u8f66","price":"193.8","year":"2007","max_year":"2011","min_year":"2007"},{"key":"22473","brand_id":"7","series_id":"103","value":"2006\u6b3e 630i 3.0L \u53cc\u95e8\u8f7f\u8dd1\u8f66","nameL":"2006\u6b3e \u5b9d\u9a6c6\u7cfb 630i 3.0L \u53cc\u95e8\u8f7f\u8dd1\u8f66","price":"107.4","year":"2006","max_year":"2008","min_year":"2006"},{"key":"22474","brand_id":"7","series_id":"103","value":"2006\u6b3e 630i 3.0L \u655e\u7bf7\u8f7f\u8dd1\u8f66","nameL":"2006\u6b3e \u5b9d\u9a6c6\u7cfb 630i 3.0L \u655e\u7bf7\u8f7f\u8dd1\u8f66","price":"113.5","year":"2006","max_year":"2008","min_year":"2006"},{"key":"22475","brand_id":"7","series_id":"103","value":"2006\u6b3e 650i 4.8L \u53cc\u95e8\u8f7f\u8dd1\u8f66","nameL":"2006\u6b3e \u5b9d\u9a6c6\u7cfb 650i 4.8L \u53cc\u95e8\u8f7f\u8dd1\u8f66","price":"184.8","year":"2006","max_year":"2008","min_year":"2006"},{"key":"22476","brand_id":"7","series_id":"103","value":"2006\u6b3e 650i 4.8L \u655e\u7bf7\u8f7f\u8dd1\u8f66","nameL":"2006\u6b3e \u5b9d\u9a6c6\u7cfb 650i 4.8L \u655e\u7bf7\u8f7f\u8dd1\u8f66","price":"193.8","year":"2006","max_year":"2008","min_year":"2006"},{"key":"1580","brand_id":"7","series_id":"103","value":"2004\u6b3e 645ci\u53cc\u95e8\u655e\u84ec\u8f6f\u9876","nameL":"2004\u6b3e \u5b9d\u9a6c6\u7cfb 645ci\u53cc\u95e8\u655e\u84ec\u8f6f\u9876","price":"138","year":"2004","max_year":"2007","min_year":"2004"},{"key":"1581","brand_id":"7","series_id":"103","value":"2004\u6b3e 645Ci\u786c\u9876","nameL":"2004\u6b3e \u5b9d\u9a6c6\u7cfb 645Ci\u786c\u9876","price":"142","year":"2004","max_year":"2007","min_year":"2004"}]