[{"key":"16902","brand_id":"124","series_id":"1198","value":"2012\u6b3e MF4 4.4T","nameL":"2012\u6b3e \u5a01\u5179\u66fcRoadster MF4 4.4T","price":"310","year":"2012","max_year":"2016","min_year":"2012"},{"key":"16903","brand_id":"124","series_id":"1198","value":"2012\u6b3e MF5 4.4T","nameL":"2012\u6b3e \u5a01\u5179\u66fcRoadster MF5 4.4T","price":"410","year":"2012","max_year":"2016","min_year":"2012"},{"key":"28906","brand_id":"124","series_id":"1198","value":"2012\u6b3e MF4-S","nameL":"2012\u6b3e \u5a01\u5179\u66fcRoadster MF4-S","price":"320","year":"2012","max_year":"2016","min_year":"2012"}]