[{"key":"10359","brand_id":"64","series_id":"707","value":"2011\u6b3e XFR 5.0L V8 \u673a\u68b0\u589e\u538b\u7248","nameL":"2011\u6b3e \u6377\u8c79XFR 5.0L V8 \u673a\u68b0\u589e\u538b\u7248","price":"188","year":"2011","max_year":"2015","min_year":"2010"},{"key":"10360","brand_id":"64","series_id":"707","value":"2009\u6b3e XFR 5.0L V8\u673a\u68b0\u589e\u538b\u7248","nameL":"2009\u6b3e \u6377\u8c79XFR 5.0L V8\u673a\u68b0\u589e\u538b\u7248","price":"188.8","year":"2009","max_year":"2013","min_year":"2008"}]