[{"key":"29438","brand_id":"9","series_id":"2437","value":"2016\u6b3e 200 4MATIC","nameL":"2016\u6b3e \u5954\u9a70GLC\u7ea7 200 4MATIC","price":"39.6","year":"2016","max_year":"2016","min_year":"2015"},{"key":"29439","brand_id":"9","series_id":"2437","value":"2016\u6b3e 260 4MATIC \u52a8\u611f\u578b","nameL":"2016\u6b3e \u5954\u9a70GLC\u7ea7 260 4MATIC \u52a8\u611f\u578b","price":"42.8","year":"2016","max_year":"2016","min_year":"2015"},{"key":"29440","brand_id":"9","series_id":"2437","value":"2016\u6b3e 260 4MATIC \u8c6a\u534e\u578b","nameL":"2016\u6b3e \u5954\u9a70GLC\u7ea7 260 4MATIC \u8c6a\u534e\u578b","price":"44.3","year":"2016","max_year":"2016","min_year":"2015"},{"key":"29441","brand_id":"9","series_id":"2437","value":"2016\u6b3e 300 4MATIC \u52a8\u611f\u578b","nameL":"2016\u6b3e \u5954\u9a70GLC\u7ea7 300 4MATIC \u52a8\u611f\u578b","price":"48.6","year":"2016","max_year":"2016","min_year":"2015"},{"key":"29442","brand_id":"9","series_id":"2437","value":"2016\u6b3e 300 4MATIC \u8c6a\u534e\u578b","nameL":"2016\u6b3e \u5954\u9a70GLC\u7ea7 300 4MATIC \u8c6a\u534e\u578b","price":"57.9","year":"2016","max_year":"2016","min_year":"2015"}]