[{"key":"29391","brand_id":"22","series_id":"264","value":"2016\u6b3e 1.5L \u624b\u52a8\u8212\u9002\u578b","nameL":"2016\u6b3e \u957f\u57ceC30 1.5L \u624b\u52a8\u8212\u9002\u578b","price":"6.29","year":"2016","max_year":"2016","min_year":"2015"},{"key":"29392","brand_id":"22","series_id":"264","value":"2016\u6b3e 1.5L \u624b\u52a8\u8c6a\u534e\u578b","nameL":"2016\u6b3e \u957f\u57ceC30 1.5L \u624b\u52a8\u8c6a\u534e\u578b","price":"6.69","year":"2016","max_year":"2016","min_year":"2015"},{"key":"29394","brand_id":"22","series_id":"264","value":"2016\u6b3e 1.5L AMT\u8212\u9002\u578b","nameL":"2016\u6b3e \u957f\u57ceC30 1.5L AMT\u8212\u9002\u578b","price":"6.79","year":"2016","max_year":"2016","min_year":"2015"},{"key":"29393","brand_id":"22","series_id":"264","value":"2016\u6b3e 1.5L \u624b\u52a8\u7cbe\u82f1\u578b","nameL":"2016\u6b3e \u957f\u57ceC30 1.5L \u624b\u52a8\u7cbe\u82f1\u578b","price":"7.09","year":"2016","max_year":"2016","min_year":"2015"},{"key":"29395","brand_id":"22","series_id":"264","value":"2016\u6b3e 1.5L AMT\u8c6a\u534e\u578b","nameL":"2016\u6b3e \u957f\u57ceC30 1.5L AMT\u8c6a\u534e\u578b","price":"7.19","year":"2016","max_year":"2016","min_year":"2015"},{"key":"28330","brand_id":"22","series_id":"264","value":"2015\u6b3e \u7ecf\u5178\u7248 1.5L \u624b\u52a8\u7545\u4eab\u578b","nameL":"2015\u6b3e \u957f\u57ceC30 \u7ecf\u5178\u7248 1.5L \u624b\u52a8\u7545\u4eab\u578b","price":"5.49","year":"2015","max_year":"2016","min_year":"2015"},{"key":"28331","brand_id":"22","series_id":"264","value":"2015\u6b3e \u7ecf\u5178\u7248 1.5L \u624b\u52a8\u60a6\u4eab\u578b","nameL":"2015\u6b3e \u957f\u57ceC30 \u7ecf\u5178\u7248 1.5L \u624b\u52a8\u60a6\u4eab\u578b","price":"5.89","year":"2015","max_year":"2016","min_year":"2015"},{"key":"23507","brand_id":"22","series_id":"264","value":"2015\u6b3e 1.5L \u624b\u52a8\u8212\u9002\u578b","nameL":"2015\u6b3e \u957f\u57ceC30 1.5L \u624b\u52a8\u8212\u9002\u578b","price":"6.65","year":"2015","max_year":"2016","min_year":"2014"},{"key":"25480","brand_id":"22","series_id":"264","value":"2015\u6b3e 1.5L AMT\u8212\u9002\u578b","nameL":"2015\u6b3e \u957f\u57ceC30 1.5L AMT\u8212\u9002\u578b","price":"7.15","year":"2015","max_year":"2016","min_year":"2014"},{"key":"23508","brand_id":"22","series_id":"264","value":"2015\u6b3e 1.5L \u624b\u52a8\u8212\u9002\u578bCNG","nameL":"2015\u6b3e \u957f\u57ceC30 1.5L \u624b\u52a8\u8212\u9002\u578bCNG","price":"7.15","year":"2015","max_year":"2016","min_year":"2014"},{"key":"23510","brand_id":"22","series_id":"264","value":"2015\u6b3e 1.5L \u624b\u52a8\u8c6a\u534e\u578b","nameL":"2015\u6b3e \u957f\u57ceC30 1.5L \u624b\u52a8\u8c6a\u534e\u578b","price":"7.15","year":"2015","max_year":"2016","min_year":"2014"},{"key":"23511","brand_id":"22","series_id":"264","value":"2015\u6b3e 1.5L \u624b\u52a8\u8c6a\u534e\u578bCNG","nameL":"2015\u6b3e \u957f\u57ceC30 1.5L \u624b\u52a8\u8c6a\u534e\u578bCNG","price":"7.45","year":"2015","max_year":"2016","min_year":"2014"},{"key":"23513","brand_id":"22","series_id":"264","value":"2015\u6b3e 1.5L \u624b\u52a8\u7cbe\u82f1\u578b","nameL":"2015\u6b3e \u957f\u57ceC30 1.5L \u624b\u52a8\u7cbe\u82f1\u578b","price":"7.55","year":"2015","max_year":"2016","min_year":"2014"},{"key":"25481","brand_id":"22","series_id":"264","value":"2015\u6b3e 1.5L AMT\u8c6a\u534e\u578b","nameL":"2015\u6b3e \u957f\u57ceC30 1.5L AMT\u8c6a\u534e\u578b","price":"7.65","year":"2015","max_year":"2016","min_year":"2014"},{"key":"25482","brand_id":"22","series_id":"264","value":"2015\u6b3e 1.5L AMT\u7cbe\u82f1\u578b","nameL":"2015\u6b3e \u957f\u57ceC30 1.5L AMT\u7cbe\u82f1\u578b","price":"7.95","year":"2015","max_year":"2016","min_year":"2014"},{"key":"3254","brand_id":"22","series_id":"264","value":"2014\u6b3e \u65b0\u89c6\u754c\u7248 1.5L \u624b\u52a8 \u65f6\u5c1a\u578b","nameL":"2014\u6b3e \u957f\u57ceC30 \u65b0\u89c6\u754c\u7248 1.5L \u624b\u52a8 \u65f6\u5c1a\u578b","price":"6.45","year":"2014","max_year":"2016","min_year":"2013"},{"key":"3255","brand_id":"22","series_id":"264","value":"2014\u6b3e \u65b0\u89c6\u754c\u7248 1.5L \u624b\u52a8 \u667a\u5c1a\u578b","nameL":"2014\u6b3e \u957f\u57ceC30 \u65b0\u89c6\u754c\u7248 1.5L \u624b\u52a8 \u667a\u5c1a\u578b","price":"6.95","year":"2014","max_year":"2016","min_year":"2013"},{"key":"3256","brand_id":"22","series_id":"264","value":"2013\u6b3e 1.5L \u624b\u52a8 \u8212\u9002\u578b","nameL":"2013\u6b3e \u957f\u57ceC30 1.5L \u624b\u52a8 \u8212\u9002\u578b","price":"6.45","year":"2013","max_year":"2016","min_year":"2012"},{"key":"3257","brand_id":"22","series_id":"264","value":"2013\u6b3e 1.5L \u624b\u52a8 \u667a\u80fd\u8d77\u505c\u7248","nameL":"2013\u6b3e \u957f\u57ceC30 1.5L \u624b\u52a8 \u667a\u80fd\u8d77\u505c\u7248","price":"6.65","year":"2013","max_year":"2016","min_year":"2012"},{"key":"3258","brand_id":"22","series_id":"264","value":"2013\u6b3e 1.5L \u624b\u52a8 \u8c6a\u534e\u578b","nameL":"2013\u6b3e \u957f\u57ceC30 1.5L \u624b\u52a8 \u8c6a\u534e\u578b","price":"6.75","year":"2013","max_year":"2016","min_year":"2012"},{"key":"3259","brand_id":"22","series_id":"264","value":"2013\u6b3e 1.5L \u624b\u52a8 \u7cbe\u82f1\u578b","nameL":"2013\u6b3e \u957f\u57ceC30 1.5L \u624b\u52a8 \u7cbe\u82f1\u578b","price":"7.35","year":"2013","max_year":"2016","min_year":"2012"},{"key":"3260","brand_id":"22","series_id":"264","value":"2013\u6b3e 1.5L CVT \u8212\u9002\u578b","nameL":"2013\u6b3e \u957f\u57ceC30 1.5L CVT \u8212\u9002\u578b","price":"7.45","year":"2013","max_year":"2016","min_year":"2012"},{"key":"3261","brand_id":"22","series_id":"264","value":"2013\u6b3e 1.5L CVT \u8c6a\u534e\u578b","nameL":"2013\u6b3e \u957f\u57ceC30 1.5L CVT \u8c6a\u534e\u578b","price":"7.75","year":"2013","max_year":"2016","min_year":"2012"},{"key":"3262","brand_id":"22","series_id":"264","value":"2013\u6b3e 1.5L CVT \u7cbe\u82f1\u578b","nameL":"2013\u6b3e \u957f\u57ceC30 1.5L CVT \u7cbe\u82f1\u578b","price":"8.35","year":"2013","max_year":"2016","min_year":"2012"},{"key":"3263","brand_id":"22","series_id":"264","value":"2012\u6b3e 1.5L VVT \u624b\u52a8 \u8212\u9002\u578b","nameL":"2012\u6b3e \u957f\u57ceC30 1.5L VVT \u624b\u52a8 \u8212\u9002\u578b","price":"6.45","year":"2012","max_year":"2014","min_year":"2011"},{"key":"3264","brand_id":"22","series_id":"264","value":"2012\u6b3e 1.5L VVT \u624b\u52a8 \u667a\u80fd\u8d77\u505c\u7248","nameL":"2012\u6b3e \u957f\u57ceC30 1.5L VVT \u624b\u52a8 \u667a\u80fd\u8d77\u505c\u7248","price":"6.65","year":"2012","max_year":"2014","min_year":"2012"},{"key":"3265","brand_id":"22","series_id":"264","value":"2012\u6b3e 1.5L VVT \u624b\u52a8 \u8c6a\u534e\u578b","nameL":"2012\u6b3e \u957f\u57ceC30 1.5L VVT \u624b\u52a8 \u8c6a\u534e\u578b","price":"6.75","year":"2012","max_year":"2014","min_year":"2011"},{"key":"3266","brand_id":"22","series_id":"264","value":"2012\u6b3e 1.5L VVT \u624b\u52a8 \u7cbe\u82f1\u578b","nameL":"2012\u6b3e \u957f\u57ceC30 1.5L VVT \u624b\u52a8 \u7cbe\u82f1\u578b","price":"7.35","year":"2012","max_year":"2014","min_year":"2011"},{"key":"3267","brand_id":"22","series_id":"264","value":"2012\u6b3e 1.5L VVT CVT \u8212\u9002\u578b","nameL":"2012\u6b3e \u957f\u57ceC30 1.5L VVT CVT \u8212\u9002\u578b","price":"7.45","year":"2012","max_year":"2014","min_year":"2011"},{"key":"3268","brand_id":"22","series_id":"264","value":"2012\u6b3e 1.5L VVT CVT \u8c6a\u534e\u578b","nameL":"2012\u6b3e \u957f\u57ceC30 1.5L VVT CVT \u8c6a\u534e\u578b","price":"7.75","year":"2012","max_year":"2014","min_year":"2011"},{"key":"3269","brand_id":"22","series_id":"264","value":"2012\u6b3e 1.5L VVT CVT \u7cbe\u82f1\u578b","nameL":"2012\u6b3e \u957f\u57ceC30 1.5L VVT CVT \u7cbe\u82f1\u578b","price":"8.35","year":"2012","max_year":"2014","min_year":"2011"},{"key":"3270","brand_id":"22","series_id":"264","value":"2010\u6b3e 1.5L VVT MT \u6807\u51c6\u578b","nameL":"2010\u6b3e \u957f\u57ceC30 1.5L VVT MT \u6807\u51c6\u578b","price":"5.89","year":"2010","max_year":"2013","min_year":"2010"},{"key":"3271","brand_id":"22","series_id":"264","value":"2010\u6b3e 1.5L VVT MT \u8212\u9002\u578b","nameL":"2010\u6b3e \u957f\u57ceC30 1.5L VVT MT \u8212\u9002\u578b","price":"6.29","year":"2010","max_year":"2013","min_year":"2010"},{"key":"3272","brand_id":"22","series_id":"264","value":"2010\u6b3e 1.5L VVT MT \u8c6a\u534e\u578b","nameL":"2010\u6b3e \u957f\u57ceC30 1.5L VVT MT \u8c6a\u534e\u578b","price":"6.59","year":"2010","max_year":"2013","min_year":"2010"},{"key":"3273","brand_id":"22","series_id":"264","value":"2010\u6b3e 1.5L VVT MT \u7cbe\u82f1\u578b","nameL":"2010\u6b3e \u957f\u57ceC30 1.5L VVT MT \u7cbe\u82f1\u578b","price":"7.19","year":"2010","max_year":"2013","min_year":"2010"},{"key":"3274","brand_id":"22","series_id":"264","value":"2010\u6b3e 1.5L VVT CVT \u8212\u9002\u578b","nameL":"2010\u6b3e \u957f\u57ceC30 1.5L VVT CVT \u8212\u9002\u578b","price":"7.29","year":"2010","max_year":"2013","min_year":"2010"},{"key":"3275","brand_id":"22","series_id":"264","value":"2010\u6b3e 1.5L VVT CVT \u8c6a\u534e\u578b","nameL":"2010\u6b3e \u957f\u57ceC30 1.5L VVT CVT \u8c6a\u534e\u578b","price":"7.59","year":"2010","max_year":"2013","min_year":"2010"},{"key":"3276","brand_id":"22","series_id":"264","value":"2010\u6b3e 1.5L VVT CVT \u7cbe\u82f1\u578b","nameL":"2010\u6b3e \u957f\u57ceC30 1.5L VVT CVT \u7cbe\u82f1\u578b","price":"8.19","year":"2010","max_year":"2013","min_year":"2010"}]