[{"key":"1962","brand_id":"9","series_id":"138","value":"2014\u6b3e \u53a2\u5f0f\u8f66 2.2T 85kw \u4e2d\u8f74\u7248","nameL":"2014\u6b3e \u51cc\u7279 \u53a2\u5f0f\u8f66 2.1T 85kw \u4e2d\u8f74\u7248","price":"31.8","year":"2014","max_year":"2016","min_year":"2013"},{"key":"1963","brand_id":"9","series_id":"138","value":"2014\u6b3e \u53a2\u5f0f\u8f66 2.2T 110kw \u4e2d\u8f74\u7248","nameL":"2014\u6b3e \u51cc\u7279 \u53a2\u5f0f\u8f66 2.1T 110kw \u4e2d\u8f74\u7248","price":"33.8","year":"2014","max_year":"2016","min_year":"2013"},{"key":"1964","brand_id":"9","series_id":"138","value":"2014\u6b3e \u53a2\u5f0f\u8f66 2.2T 110kw \u957f\u8f74\u7248","nameL":"2014\u6b3e \u51cc\u7279 \u53a2\u5f0f\u8f66 2.1T 110kw \u957f\u8f74\u7248","price":"36.8","year":"2014","max_year":"2016","min_year":"2013"},{"key":"1965","brand_id":"9","series_id":"138","value":"2014\u6b3e \u53a2\u5f0f\u8f66 2.2T 110kw \u957f\u8f74\u52a0\u957f\u7248","nameL":"2014\u6b3e \u51cc\u7279 \u53a2\u5f0f\u8f66 2.1T 110kw \u957f\u8f74\u52a0\u957f\u7248","price":"37.8","year":"2014","max_year":"2016","min_year":"2013"},{"key":"1966","brand_id":"9","series_id":"138","value":"2014\u6b3e \u4f73\u65c5 2.2L \u624b\u52a8 \u4e2d\u8f74\u7248 8\u5ea7","nameL":"2014\u6b3e \u51cc\u7279 \u4f73\u65c5 2.2L \u624b\u52a8 \u4e2d\u8f74\u7248 8\u5ea7","price":"36.8","year":"2014","max_year":"2016","min_year":"2013"},{"key":"1967","brand_id":"9","series_id":"138","value":"2014\u6b3e \u4f73\u65c5 2.2L \u624b\u52a8 \u957f\u8f74\u7248 10\u5ea7","nameL":"2014\u6b3e \u51cc\u7279 \u4f73\u65c5 2.2L \u624b\u52a8 \u957f\u8f74\u7248 10\u5ea7","price":"37.8","year":"2014","max_year":"2016","min_year":"2013"},{"key":"1968","brand_id":"9","series_id":"138","value":"2014\u6b3e \u4f73\u65c5 2.2L \u624b\u52a8 \u957f\u8f74\u52a0\u957f\u7248 10\u5ea7","nameL":"2014\u6b3e \u51cc\u7279 \u4f73\u65c5 2.2L \u624b\u52a8 \u957f\u8f74\u52a0\u957f\u7248 10\u5ea7","price":"38.8","year":"2014","max_year":"2016","min_year":"2013"},{"key":"1969","brand_id":"9","series_id":"138","value":"2014\u6b3e \u5c0a\u65c5 2.2L \u624b\u52a8 \u4e2d\u8f74\u7248 8\u5ea7","nameL":"2014\u6b3e \u51cc\u7279 \u5c0a\u65c5 2.2L \u624b\u52a8 \u4e2d\u8f74\u7248 8\u5ea7","price":"40.8","year":"2014","max_year":"2016","min_year":"2013"},{"key":"1970","brand_id":"9","series_id":"138","value":"2014\u6b3e \u5c0a\u65c5 2.2L \u624b\u52a8 \u957f\u8f74\u7248 10\u5ea7","nameL":"2014\u6b3e \u51cc\u7279 \u5c0a\u65c5 2.2L \u624b\u52a8 \u957f\u8f74\u7248 10\u5ea7","price":"41.8","year":"2014","max_year":"2016","min_year":"2013"},{"key":"1971","brand_id":"9","series_id":"138","value":"2014\u6b3e \u5c0a\u65c5 2.2L \u624b\u52a8 \u957f\u8f74\u52a0\u957f\u7248 10\u5ea7","nameL":"2014\u6b3e \u51cc\u7279 \u5c0a\u65c5 2.2L \u624b\u52a8 \u957f\u8f74\u52a0\u957f\u7248 10\u5ea7","price":"42.8","year":"2014","max_year":"2016","min_year":"2013"},{"key":"1972","brand_id":"9","series_id":"138","value":"2013\u6b3e \u4f73\u65c5 2.2L \u624b\u52a8 \u957f\u8f74\u7248 17\u5ea7","nameL":"2013\u6b3e \u51cc\u7279 \u4f73\u65c5 2.2L \u624b\u52a8 \u957f\u8f74\u7248 17\u5ea7","price":"38.8","year":"2013","max_year":"2015","min_year":"2012"},{"key":"1973","brand_id":"9","series_id":"138","value":"2013\u6b3e \u4f73\u65c5 2.2L \u624b\u52a8 \u957f\u8f74\u52a0\u957f\u7248 20\u5ea7","nameL":"2013\u6b3e \u51cc\u7279 \u4f73\u65c5 2.2L \u624b\u52a8 \u957f\u8f74\u52a0\u957f\u7248 20\u5ea7","price":"40.6","year":"2013","max_year":"2015","min_year":"2012"},{"key":"1974","brand_id":"9","series_id":"138","value":"2013\u6b3e \u5c0a\u65c5 2.2L \u624b\u52a8 \u4e2d\u8f74\u7248 14\u5ea7","nameL":"2013\u6b3e \u51cc\u7279 \u5c0a\u65c5 2.2L \u624b\u52a8 \u4e2d\u8f74\u7248 14\u5ea7","price":"41.8","year":"2013","max_year":"2015","min_year":"2012"},{"key":"1975","brand_id":"9","series_id":"138","value":"2013\u6b3e \u5c0a\u65c5 2.2L \u624b\u52a8 \u957f\u8f74\u7248 17\u5ea7","nameL":"2013\u6b3e \u51cc\u7279 \u5c0a\u65c5 2.2L \u624b\u52a8 \u957f\u8f74\u7248 17\u5ea7","price":"43.8","year":"2013","max_year":"2015","min_year":"2012"},{"key":"1976","brand_id":"9","series_id":"138","value":"2013\u6b3e \u5c0a\u65c5 2.2L \u624b\u52a8 \u957f\u8f74\u52a0\u957f\u7248 20\u5ea7","nameL":"2013\u6b3e \u51cc\u7279 \u5c0a\u65c5 2.2L \u624b\u52a8 \u957f\u8f74\u52a0\u957f\u7248 20\u5ea7","price":"45.8","year":"2013","max_year":"2015","min_year":"2012"},{"key":"1978","brand_id":"9","series_id":"138","value":"2012\u6b3e \u53a2\u5f0f\u8f66 2.2L \u624b\u52a8 \u57fa\u672c\u578b85kw","nameL":"2012\u6b3e \u51cc\u7279 \u53a2\u5f0f\u8f66 2.1L \u624b\u52a8 \u57fa\u672c\u578b85kw","price":"31.8","year":"2012","max_year":"2016","min_year":"2011"},{"key":"1979","brand_id":"9","series_id":"138","value":"2012\u6b3e \u53a2\u5f0f\u8f66 2.2L \u624b\u52a8 \u57fa\u672c\u578b110kw","nameL":"2012\u6b3e \u51cc\u7279 \u53a2\u5f0f\u8f66 2.1L \u624b\u52a8 \u57fa\u672c\u578b110kw","price":"33.8","year":"2012","max_year":"2016","min_year":"2011"},{"key":"1980","brand_id":"9","series_id":"138","value":"2012\u6b3e \u4f73\u65c5 2.2L \u624b\u52a8 \u957f\u8f74\u7248 17\u5ea7","nameL":"2012\u6b3e \u51cc\u7279 \u4f73\u65c5 2.1L \u624b\u52a8 \u957f\u8f74\u7248 17\u5ea7","price":"38.8","year":"2012","max_year":"2016","min_year":"2011"},{"key":"1977","brand_id":"9","series_id":"138","value":"2012\u6b3e \u4f73\u65c5 2.2L \u624b\u52a8 \u957f\u8f74\u52a0\u957f\u7248 20\u5ea7","nameL":"2012\u6b3e \u51cc\u7279 \u4f73\u65c5 2.1L \u624b\u52a8 \u957f\u8f74\u52a0\u957f\u7248 20\u5ea7","price":"39.6","year":"2012","max_year":"2016","min_year":"2011"},{"key":"1981","brand_id":"9","series_id":"138","value":"2012\u6b3e \u4f73\u65c5 2.2L \u624b\u52a8 \u957f\u8f74\u52a0\u957f\u7248 17\u5ea7","nameL":"2012\u6b3e \u51cc\u7279 \u4f73\u65c5 2.1L \u624b\u52a8 \u957f\u8f74\u52a0\u957f\u7248 17\u5ea7","price":"39.8","year":"2012","max_year":"2016","min_year":"2011"},{"key":"1982","brand_id":"9","series_id":"138","value":"2012\u6b3e \u5c0a\u65c5 2.2L \u624b\u52a8 \u4e2d\u8f74\u7248 14\u5ea7","nameL":"2012\u6b3e \u51cc\u7279 \u5c0a\u65c5 2.1L \u624b\u52a8 \u4e2d\u8f74\u7248 14\u5ea7","price":"41.8","year":"2012","max_year":"2016","min_year":"2011"},{"key":"1983","brand_id":"9","series_id":"138","value":"2012\u6b3e \u5c0a\u65c5 2.2L \u624b\u52a8 \u957f\u8f74\u7248 17\u5ea7","nameL":"2012\u6b3e \u51cc\u7279 \u5c0a\u65c5 2.1L \u624b\u52a8 \u957f\u8f74\u7248 17\u5ea7","price":"43.8","year":"2012","max_year":"2016","min_year":"2011"},{"key":"1984","brand_id":"9","series_id":"138","value":"2012\u6b3e \u5c0a\u65c5 2.1L \u624b\u52a8 \u957f\u8f74\u52a0\u957f\u7248 17\u5ea7","nameL":"2012\u6b3e \u51cc\u7279 \u5c0a\u65c5 2.1L \u624b\u52a8 \u957f\u8f74\u52a0\u957f\u7248 17\u5ea7","price":"44.8","year":"2012","max_year":"2016","min_year":"2011"},{"key":"1985","brand_id":"9","series_id":"138","value":"2012\u6b3e \u5c0a\u65c5 2.2L \u624b\u52a8 \u957f\u8f74\u52a0\u957f\u7248 20\u5ea7","nameL":"2012\u6b3e \u51cc\u7279 \u5c0a\u65c5 2.1L \u624b\u52a8 \u957f\u8f74\u52a0\u957f\u7248 20\u5ea7","price":"45.8","year":"2012","max_year":"2016","min_year":"2011"},{"key":"1986","brand_id":"9","series_id":"138","value":"2011\u6b3e \u5c0a\u65c5 2.2L \u624b\u52a8 \u4e2d\u8f74\u7248(14\u5ea7)T1 A2","nameL":"2011\u6b3e \u51cc\u7279 \u5c0a\u65c5 2.1L \u624b\u52a8 \u4e2d\u8f74\u7248(14\u5ea7)T1 A2","price":"41.8","year":"2011","max_year":"2013","min_year":"2010"},{"key":"1987","brand_id":"9","series_id":"138","value":"2011\u6b3e \u5c0a\u65c5 2.2L \u624b\u52a8 \u957f\u8f74\u7248(17\u5ea7)T1 A3","nameL":"2011\u6b3e \u51cc\u7279 \u5c0a\u65c5 2.1L \u624b\u52a8 \u957f\u8f74\u7248(17\u5ea7)T1 A3","price":"43.8","year":"2011","max_year":"2013","min_year":"2010"},{"key":"1988","brand_id":"9","series_id":"138","value":"2011\u6b3e \u5c0a\u65c5 2.2L \u624b\u52a8 \u957f\u8f74\u52a0\u957f\u7248(17\u5ea7)T1 A4","nameL":"2011\u6b3e \u51cc\u7279 \u5c0a\u65c5 2.1L \u624b\u52a8 \u957f\u8f74\u52a0\u957f\u7248(17\u5ea7)T1 A4","price":"44.8","year":"2011","max_year":"2013","min_year":"2010"},{"key":"1989","brand_id":"9","series_id":"138","value":"2011\u6b3e \u5c0a\u65c5 2.2L \u624b\u52a8 \u957f\u8f74\u52a0\u957f\u7248(20\u5ea7)T1 A4","nameL":"2011\u6b3e \u51cc\u7279 \u5c0a\u65c5 2.1L \u624b\u52a8 \u957f\u8f74\u52a0\u957f\u7248(20\u5ea7)T1 A4","price":"45.8","year":"2011","max_year":"2013","min_year":"2010"},{"key":"1990","brand_id":"9","series_id":"138","value":"2011\u6b3e 2.2L \u624b\u52a8 \u957f\u8f74\u7248(14\u5ea7)","nameL":"2011\u6b3e \u51cc\u7279 2.2L \u624b\u52a8 \u957f\u8f74\u7248(14\u5ea7)","price":"43.2","year":"2011","max_year":"2013","min_year":"2010"}]