[{"key":"6930","brand_id":"37","series_id":"476","value":"2006\u6b3e 1.5 GSX","nameL":"2006\u6b3e \u5468\u672b\u98ce 1.5 GSX","price":"7.26","year":"2006","max_year":"2010","min_year":"2006"},{"key":"6931","brand_id":"37","series_id":"476","value":"2006\u6b3e 1.5 GL","nameL":"2006\u6b3e \u5468\u672b\u98ce 1.5 GL","price":"7.86","year":"2006","max_year":"2010","min_year":"2006"},{"key":"6933","brand_id":"37","series_id":"476","value":"2006\u6b3e 1.5 GL AT","nameL":"2006\u6b3e \u5468\u672b\u98ce 1.5 GL AT","price":"8.91","year":"2006","max_year":"2010","min_year":"2006"},{"key":"6932","brand_id":"37","series_id":"476","value":"2006\u6b3e 1.5 GLX","nameL":"2006\u6b3e \u5468\u672b\u98ce 1.5 GLX","price":"9.16","year":"2006","max_year":"2010","min_year":"2006"},{"key":"6934","brand_id":"37","series_id":"476","value":"2005\u6b3e 1.5FSX \u5341\u8fd0\u5409\u7965\u7248","nameL":"2005\u6b3e \u5468\u672b\u98ce 1.5FSX \u5341\u8fd0\u5409\u7965\u7248","price":"8.08","year":"2005","max_year":"2007","min_year":"2005"},{"key":"6935","brand_id":"37","series_id":"476","value":"2005\u6b3e 1.5FSX","nameL":"2005\u6b3e \u5468\u672b\u98ce 1.5FSX","price":"8.08","year":"2005","max_year":"2007","min_year":"2005"},{"key":"6936","brand_id":"37","series_id":"476","value":"2005\u6b3e 1.5FL","nameL":"2005\u6b3e \u5468\u672b\u98ce 1.5FL","price":"8.68","year":"2005","max_year":"2007","min_year":"2005"},{"key":"6937","brand_id":"37","series_id":"476","value":"2005\u6b3e 1.5FLX","nameL":"2005\u6b3e \u5468\u672b\u98ce 1.5FLX","price":"9.98","year":"2005","max_year":"2007","min_year":"2005"},{"key":"6938","brand_id":"37","series_id":"476","value":"2005\u6b3e 1.5FL\/AT","nameL":"2005\u6b3e \u5468\u672b\u98ce 1.5FL\/AT","price":"9.98","year":"2005","max_year":"2007","min_year":"2005"},{"key":"6939","brand_id":"37","series_id":"476","value":"2004\u6b3e 1.3HLX-Speedgear","nameL":"2004\u6b3e \u5468\u672b\u98ce 1.3HLX-Speedgear","price":"11.68","year":"2004","max_year":"2006","min_year":"2004"},{"key":"6940","brand_id":"37","series_id":"476","value":"2004\u6b3e 1.5HL","nameL":"2004\u6b3e \u5468\u672b\u98ce 1.5HL","price":"8.68","year":"2004","max_year":"2006","min_year":"2004"},{"key":"6942","brand_id":"37","series_id":"476","value":"2004\u6b3e 1.5HL\/AT","nameL":"2004\u6b3e \u5468\u672b\u98ce 1.5HL\/AT","price":"10.28","year":"2004","max_year":"2006","min_year":"2004"},{"key":"6941","brand_id":"37","series_id":"476","value":"2004\u6b3e 1.5HLX","nameL":"2004\u6b3e \u5468\u672b\u98ce 1.5HLX","price":"10.58","year":"2004","max_year":"2006","min_year":"2004"},{"key":"6943","brand_id":"37","series_id":"476","value":"2004\u6b3e 1.5HLX-Speedgear","nameL":"2004\u6b3e \u5468\u672b\u98ce 1.5HLX-Speedgear","price":"10.58","year":"2004","max_year":"2006","min_year":"2004"},{"key":"6944","brand_id":"37","series_id":"476","value":"2003\u6b3e Speedgear","nameL":"2003\u6b3e \u5468\u672b\u98ce Speedgear","price":"12.19","year":"2003","max_year":"2005","min_year":"2003"},{"key":"6945","brand_id":"37","series_id":"476","value":"2003\u6b3e EL","nameL":"2003\u6b3e \u5468\u672b\u98ce EL","price":"9.68","year":"2003","max_year":"2005","min_year":"2003"},{"key":"6946","brand_id":"37","series_id":"476","value":"2003\u6b3e ELX","nameL":"2003\u6b3e \u5468\u672b\u98ce ELX","price":"12.19","year":"2003","max_year":"2005","min_year":"2003"}]