[{"key":"22382","brand_id":"36","series_id":"467","value":"2007\u6b3e 2.4 \u81ea\u52a8\u7248","nameL":"2007\u6b3e \u4e30\u7530\u4f73\u7f8e(\u8fdb\u53e3) 2.4 \u81ea\u52a8\u7248","price":"33.68","year":"2007","max_year":"2011","min_year":"2007"},{"key":"6864","brand_id":"36","series_id":"467","value":"2004\u6b3e 2.0 \u6807\u51c6\u7248","nameL":"2004\u6b3e \u4e30\u7530\u4f73\u7f8e(\u8fdb\u53e3) 2.0 \u6807\u51c6\u7248","price":"31.5","year":"2004","max_year":"2008","min_year":"2003"},{"key":"22383","brand_id":"36","series_id":"467","value":"2004\u6b3e 2.4 \u81ea\u52a8\u7248","nameL":"2004\u6b3e \u4e30\u7530\u4f73\u7f8e(\u8fdb\u53e3) 2.4 \u81ea\u52a8\u7248","price":"33.68","year":"2004","max_year":"2008","min_year":"2004"}]