[{"key":"22296","brand_id":"45","series_id":"544","value":"2012\u6b3e 2.2T\u83b1\u52a8\u67f4\u6cb9\u8212\u9002\u578b\u6807\u51c6\u8d27\u7bb1","nameL":"2012\u6b3e \u8d22\u8fd0100 2.2T\u83b1\u52a8\u67f4\u6cb9\u8212\u9002\u578b\u6807\u51c6\u8d27\u7bb1","price":"5.49","year":"2012","max_year":"2016","min_year":"2012"},{"key":"22297","brand_id":"45","series_id":"544","value":"2012\u6b3e 2.2T\u83b1\u52a8\u67f4\u6cb9\u8212\u9002\u578b\u52a0\u957f\u8d27\u7bb1","nameL":"2012\u6b3e \u8d22\u8fd0100 2.2T\u83b1\u52a8\u67f4\u6cb9\u8212\u9002\u578b\u52a0\u957f\u8d27\u7bb1","price":"5.69","year":"2012","max_year":"2016","min_year":"2012"},{"key":"22298","brand_id":"45","series_id":"544","value":"2012\u6b3e 2.2T\u83b1\u52a8\u67f4\u6cb9\u6807\u51c6\u578b\u6807\u51c6\u8d27\u7bb1","nameL":"2012\u6b3e \u8d22\u8fd0100 2.2T\u83b1\u52a8\u67f4\u6cb9\u6807\u51c6\u578b\u6807\u51c6\u8d27\u7bb1","price":"6.03","year":"2012","max_year":"2016","min_year":"2012"},{"key":"22299","brand_id":"45","series_id":"544","value":"2012\u6b3e 2.2T\u83b1\u52a8\u67f4\u6cb9\u6807\u51c6\u578b\u52a0\u957f\u8d27\u7bb1","nameL":"2012\u6b3e \u8d22\u8fd0100 2.2T\u83b1\u52a8\u67f4\u6cb9\u6807\u51c6\u578b\u52a0\u957f\u8d27\u7bb1","price":"6.23","year":"2012","max_year":"2016","min_year":"2012"},{"key":"22300","brand_id":"45","series_id":"544","value":"2012\u6b3e 2.2T\u83b1\u52a8\u67f4\u6cb9\u6807\u51c6\u578b\u8d85\u957f\u8d27\u7bb1","nameL":"2012\u6b3e \u8d22\u8fd0100 2.2T\u83b1\u52a8\u67f4\u6cb9\u6807\u51c6\u578b\u8d85\u957f\u8d27\u7bb1","price":"6.43","year":"2012","max_year":"2016","min_year":"2012"},{"key":"22301","brand_id":"45","series_id":"544","value":"2012\u6b3e 2.8T-VE\u6cf5\u67f4\u6cb9\u8212\u9002\u578b\u6807\u51c6\u8d27\u7bb1","nameL":"2012\u6b3e \u8d22\u8fd0100 2.8T-VE\u6cf5\u67f4\u6cb9\u8212\u9002\u578b\u6807\u51c6\u8d27\u7bb1","price":"6.35","year":"2012","max_year":"2016","min_year":"2012"},{"key":"22302","brand_id":"45","series_id":"544","value":"2012\u6b3e 2.8T-VE\u6cf5\u67f4\u6cb9\u8212\u9002\u578b\u52a0\u957f\u8d27\u7bb1","nameL":"2012\u6b3e \u8d22\u8fd0100 2.8T-VE\u6cf5\u67f4\u6cb9\u8212\u9002\u578b\u52a0\u957f\u8d27\u7bb1","price":"6.55","year":"2012","max_year":"2016","min_year":"2012"},{"key":"22304","brand_id":"45","series_id":"544","value":"2012\u6b3e 2.8T-VE\u6cf5\u67f4\u6cb9\u8c6a\u534e\u578b\u6807\u51c6\u8d27\u7bb1","nameL":"2012\u6b3e \u8d22\u8fd0100 2.8T-VE\u6cf5\u67f4\u6cb9\u8c6a\u534e\u578b\u6807\u51c6\u8d27\u7bb1","price":"6.68","year":"2012","max_year":"2016","min_year":"2012"},{"key":"22303","brand_id":"45","series_id":"544","value":"2012\u6b3e 2.8T-VE\u6cf5\u67f4\u6cb9\u8212\u9002\u578b\u8d85\u957f\u8d27\u7bb1","nameL":"2012\u6b3e \u8d22\u8fd0100 2.8T-VE\u6cf5\u67f4\u6cb9\u8212\u9002\u578b\u8d85\u957f\u8d27\u7bb1","price":"6.75","year":"2012","max_year":"2016","min_year":"2012"},{"key":"22305","brand_id":"45","series_id":"544","value":"2012\u6b3e 2.8T-VE\u6cf5\u67f4\u6cb9\u8c6a\u534e\u578b\u52a0\u957f\u8d27\u7bb1","nameL":"2012\u6b3e \u8d22\u8fd0100 2.8T-VE\u6cf5\u67f4\u6cb9\u8c6a\u534e\u578b\u52a0\u957f\u8d27\u7bb1","price":"6.88","year":"2012","max_year":"2016","min_year":"2012"},{"key":"22306","brand_id":"45","series_id":"544","value":"2012\u6b3e 2.8T-VE\u6cf5\u67f4\u6cb9\u8c6a\u534e\u578b\u8d85\u957f\u8d27\u7bb1","nameL":"2012\u6b3e \u8d22\u8fd0100 2.8T-VE\u6cf5\u67f4\u6cb9\u8c6a\u534e\u578b\u8d85\u957f\u8d27\u7bb1","price":"7.08","year":"2012","max_year":"2016","min_year":"2012"},{"key":"22307","brand_id":"45","series_id":"544","value":"2012\u6b3e 2.2L\u6c7d\u6cb9\u8212\u9002\u578b\u6807\u51c6\u8d27\u7bb1","nameL":"2012\u6b3e \u8d22\u8fd0100 2.2L\u6c7d\u6cb9\u8212\u9002\u578b\u6807\u51c6\u8d27\u7bb1","price":"5.29","year":"2012","max_year":"2016","min_year":"2012"},{"key":"22309","brand_id":"45","series_id":"544","value":"2012\u6b3e 2.2L\u6c7d\u6cb9\u6807\u51c6\u578b\u6807\u51c6\u8d27\u7bb1","nameL":"2012\u6b3e \u8d22\u8fd0100 2.2L\u6c7d\u6cb9\u6807\u51c6\u578b\u6807\u51c6\u8d27\u7bb1","price":"5.78","year":"2012","max_year":"2016","min_year":"2012"},{"key":"22308","brand_id":"45","series_id":"544","value":"2012\u6b3e 2.2L\u6c7d\u6cb9\u8212\u9002\u578b\u52a0\u957f\u8d27\u7bb1","nameL":"2012\u6b3e \u8d22\u8fd0100 2.2L\u6c7d\u6cb9\u8212\u9002\u578b\u52a0\u957f\u8d27\u7bb1","price":"5.89","year":"2012","max_year":"2016","min_year":"2012"},{"key":"22310","brand_id":"45","series_id":"544","value":"2012\u6b3e 2.2L\u6c7d\u6cb9\u6807\u51c6\u578b\u52a0\u957f\u8d27\u7bb1","nameL":"2012\u6b3e \u8d22\u8fd0100 2.2L\u6c7d\u6cb9\u6807\u51c6\u578b\u52a0\u957f\u8d27\u7bb1","price":"6.48","year":"2012","max_year":"2016","min_year":"2012"},{"key":"22311","brand_id":"45","series_id":"544","value":"2012\u6b3e 2.2L\u6c7d\u6cb9\u6807\u51c6\u578b\u8d85\u957f\u8d27\u7bb1","nameL":"2012\u6b3e \u8d22\u8fd0100 2.2L\u6c7d\u6cb9\u6807\u51c6\u578b\u8d85\u957f\u8d27\u7bb1","price":"6.68","year":"2012","max_year":"2016","min_year":"2012"},{"key":"8124","brand_id":"45","series_id":"544","value":"2010\u6b3e GA1020CRE3A\/S3BZ-9 \u7ecf\u6d4e\u578b","nameL":"2010\u6b3e \u8d22\u8fd0100 GA1020CRE3A\/S3BZ-9 \u7ecf\u6d4e\u578b","price":"5.39","year":"2010","max_year":"2013","min_year":"2009"},{"key":"8125","brand_id":"45","series_id":"544","value":"2010\u6b3e GA1020E3\/S3BZ-30 \u7ecf\u6d4e\u578b","nameL":"2010\u6b3e \u8d22\u8fd0100 GA1020E3\/S3BZ-30 \u7ecf\u6d4e\u578b","price":"5.49","year":"2010","max_year":"2013","min_year":"2009"},{"key":"8126","brand_id":"45","series_id":"544","value":"2010\u6b3e 2.2L \u83b1\u52a8\u67f4\u6cb9 \u624b\u52a8 \u8212\u9002\u578b \u52a0\u957f\u7248","nameL":"2010\u6b3e \u8d22\u8fd0100 2.2L \u83b1\u52a8\u67f4\u6cb9 \u624b\u52a8 \u8212\u9002\u578b \u52a0\u957f\u7248","price":"5.49","year":"2010","max_year":"2013","min_year":"2009"},{"key":"8127","brand_id":"45","series_id":"544","value":"2010\u6b3e 2.2L \u83b1\u52a8\u67f4\u6cb9 \u624b\u52a8 \u8212\u9002\u578b","nameL":"2010\u6b3e \u8d22\u8fd0100 2.2L \u83b1\u52a8\u67f4\u6cb9 \u624b\u52a8 \u8212\u9002\u578b","price":"5.49","year":"2010","max_year":"2013","min_year":"2009"},{"key":"8128","brand_id":"45","series_id":"544","value":"2010\u6b3e 2.2L \u6c7d\u6cb9 \u624b\u52a8 \u8212\u9002\u578b","nameL":"2010\u6b3e \u8d22\u8fd0100 2.2L \u6c7d\u6cb9 \u624b\u52a8 \u8212\u9002\u578b","price":"5.69","year":"2010","max_year":"2013","min_year":"2009"},{"key":"8129","brand_id":"45","series_id":"544","value":"2010\u6b3e \u5927\u8d22\u8fd0 GA1020LCRE3A\/S3BZT-9 \u7ecf\u6d4e\u578b","nameL":"2010\u6b3e \u8d22\u8fd0100 \u5927\u8d22\u8fd0 GA1020LCRE3A\/S3BZT-9 \u7ecf\u6d4e\u578b","price":"5.79","year":"2010","max_year":"2013","min_year":"2009"},{"key":"8130","brand_id":"45","series_id":"544","value":"2010\u6b3e 2.2L \u83b1\u52a8\u67f4\u6cb9 \u624b\u52a8 \u8212\u9002\u578b \u8d85\u957f\u7248","nameL":"2010\u6b3e \u8d22\u8fd0100 2.2L \u83b1\u52a8\u67f4\u6cb9 \u624b\u52a8 \u8212\u9002\u578b \u8d85\u957f\u7248","price":"5.89","year":"2010","max_year":"2013","min_year":"2009"},{"key":"8131","brand_id":"45","series_id":"544","value":"2010\u6b3e 2.2L \u6c7d\u6cb9 \u624b\u52a8 \u8212\u9002\u578b \u52a0\u957f\u7248","nameL":"2010\u6b3e \u8d22\u8fd0100 2.2L \u6c7d\u6cb9 \u624b\u52a8 \u8212\u9002\u578b \u52a0\u957f\u7248","price":"5.89","year":"2010","max_year":"2013","min_year":"2009"},{"key":"8132","brand_id":"45","series_id":"544","value":"2010\u6b3e 2.2L \u83b1\u52a8\u67f4\u6cb9 \u624b\u52a8 \u6807\u51c6\u578b \u52a0\u957f\u7248","nameL":"2010\u6b3e \u8d22\u8fd0100 2.2L \u83b1\u52a8\u67f4\u6cb9 \u624b\u52a8 \u6807\u51c6\u578b \u52a0\u957f\u7248","price":"6.03","year":"2010","max_year":"2013","min_year":"2009"},{"key":"8133","brand_id":"45","series_id":"544","value":"2010\u6b3e GA1020CRE3A\/B3BZ-9 \u6807\u51c6\u578b","nameL":"2010\u6b3e \u8d22\u8fd0100 GA1020CRE3A\/B3BZ-9 \u6807\u51c6\u578b","price":"6.03","year":"2010","max_year":"2013","min_year":"2009"},{"key":"8134","brand_id":"45","series_id":"544","value":"2010\u6b3e GA1020E3\/J3BZ-30 \u6807\u51c6\u578b","nameL":"2010\u6b3e \u8d22\u8fd0100 GA1020E3\/J3BZ-30 \u6807\u51c6\u578b","price":"6.08","year":"2010","max_year":"2013","min_year":"2009"},{"key":"8135","brand_id":"45","series_id":"544","value":"2010\u6b3e 2.2L \u6c7d\u6cb9 \u624b\u52a8 \u8212\u9002\u578b \u8d85\u957f\u7248","nameL":"2010\u6b3e \u8d22\u8fd0100 2.2L \u6c7d\u6cb9 \u624b\u52a8 \u8212\u9002\u578b \u8d85\u957f\u7248","price":"6.09","year":"2010","max_year":"2013","min_year":"2009"},{"key":"8136","brand_id":"45","series_id":"544","value":"2010\u6b3e 2.2L \u83b1\u52a8\u67f4\u6cb9 \u624b\u52a8 \u6807\u51c6\u578b","nameL":"2010\u6b3e \u8d22\u8fd0100 2.2L \u83b1\u52a8\u67f4\u6cb9 \u624b\u52a8 \u6807\u51c6\u578b","price":"6.23","year":"2010","max_year":"2013","min_year":"2009"},{"key":"8137","brand_id":"45","series_id":"544","value":"2010\u6b3e 2.2L \u6c7d\u6cb9 \u624b\u52a8 \u6807\u51c6\u578b","nameL":"2010\u6b3e \u8d22\u8fd0100 2.2L \u6c7d\u6cb9 \u624b\u52a8 \u6807\u51c6\u578b","price":"6.28","year":"2010","max_year":"2013","min_year":"2009"},{"key":"8138","brand_id":"45","series_id":"544","value":"2010\u6b3e \u5927\u8d22\u8fd0 GA1020LCRE3A\/B3BZT-9 \u6807\u51c6\u578b","nameL":"2010\u6b3e \u8d22\u8fd0100 \u5927\u8d22\u8fd0 GA1020LCRE3A\/B3BZT-9 \u6807\u51c6\u578b","price":"6.43","year":"2010","max_year":"2013","min_year":"2009"},{"key":"8139","brand_id":"45","series_id":"544","value":"2010\u6b3e 2.2L \u83b1\u52a8\u67f4\u6cb9 \u624b\u52a8 \u6807\u51c6\u578b \u8d85\u957f\u7248","nameL":"2010\u6b3e \u8d22\u8fd0100 2.2L \u83b1\u52a8\u67f4\u6cb9 \u624b\u52a8 \u6807\u51c6\u578b \u8d85\u957f\u7248","price":"6.43","year":"2010","max_year":"2013","min_year":"2009"},{"key":"8140","brand_id":"45","series_id":"544","value":"2010\u6b3e \u5927\u8d22\u8fd0 GA1020LE3\/J3BZT-30 \u6807\u51c6\u578b","nameL":"2010\u6b3e \u8d22\u8fd0100 \u5927\u8d22\u8fd0 GA1020LE3\/J3BZT-30 \u6807\u51c6\u578b","price":"6.48","year":"2010","max_year":"2013","min_year":"2009"},{"key":"8141","brand_id":"45","series_id":"544","value":"2010\u6b3e 2.2L \u6c7d\u6cb9 \u624b\u52a8 \u6807\u51c6\u578b \u52a0\u957f\u7248","nameL":"2010\u6b3e \u8d22\u8fd0100 2.2L \u6c7d\u6cb9 \u624b\u52a8 \u6807\u51c6\u578b \u52a0\u957f\u7248","price":"6.48","year":"2010","max_year":"2013","min_year":"2009"},{"key":"8142","brand_id":"45","series_id":"544","value":"2010\u6b3e 2.2L \u6c7d\u6cb9 \u624b\u52a8 \u6807\u51c6\u578b \u8d85\u957f\u7248","nameL":"2010\u6b3e \u8d22\u8fd0100 2.2L \u6c7d\u6cb9 \u624b\u52a8 \u6807\u51c6\u578b \u8d85\u957f\u7248","price":"6.68","year":"2010","max_year":"2013","min_year":"2009"},{"key":"8143","brand_id":"45","series_id":"544","value":"2010\u6b3e 2.8L VE\u6cf5\u67f4\u6cb9 \u624b\u52a8 \u8212\u9002\u578b","nameL":"2010\u6b3e \u8d22\u8fd0100 2.8L VE\u6cf5\u67f4\u6cb9 \u624b\u52a8 \u8212\u9002\u578b","price":"6.35","year":"2010","max_year":"2013","min_year":"2009"},{"key":"8144","brand_id":"45","series_id":"544","value":"2010\u6b3e 2.8L VE\u6cf5\u67f4\u6cb9 \u624b\u52a8 \u8212\u9002\u578b \u52a0\u957f\u7248","nameL":"2010\u6b3e \u8d22\u8fd0100 2.8L VE\u6cf5\u67f4\u6cb9 \u624b\u52a8 \u8212\u9002\u578b \u52a0\u957f\u7248","price":"6.55","year":"2010","max_year":"2013","min_year":"2009"},{"key":"8145","brand_id":"45","series_id":"544","value":"2010\u6b3e 2.8L VE\u6cf5\u67f4\u6cb9 \u624b\u52a8 \u8c6a\u534e\u578b","nameL":"2010\u6b3e \u8d22\u8fd0100 2.8L VE\u6cf5\u67f4\u6cb9 \u624b\u52a8 \u8c6a\u534e\u578b","price":"6.68","year":"2010","max_year":"2013","min_year":"2009"},{"key":"8146","brand_id":"45","series_id":"544","value":"2010\u6b3e 2.8L VE\u6cf5\u67f4\u6cb9 \u624b\u52a8 \u8212\u9002\u578b \u8d85\u957f\u7248","nameL":"2010\u6b3e \u8d22\u8fd0100 2.8L VE\u6cf5\u67f4\u6cb9 \u624b\u52a8 \u8212\u9002\u578b \u8d85\u957f\u7248","price":"6.75","year":"2010","max_year":"2013","min_year":"2009"},{"key":"8147","brand_id":"45","series_id":"544","value":"2010\u6b3e 2.8L VE\u6cf5\u67f4\u6cb9 \u624b\u52a8 \u8c6a\u534e\u578b \u52a0\u957f\u7248","nameL":"2010\u6b3e \u8d22\u8fd0100 2.8L VE\u6cf5\u67f4\u6cb9 \u624b\u52a8 \u8c6a\u534e\u578b \u52a0\u957f\u7248","price":"6.88","year":"2010","max_year":"2013","min_year":"2009"},{"key":"8148","brand_id":"45","series_id":"544","value":"2010\u6b3e 2.8L VE\u6cf5\u67f4\u6cb9 \u624b\u52a8 \u8c6a\u534e\u578b \u8d85\u957f\u7248","nameL":"2010\u6b3e \u8d22\u8fd0100 2.8L VE\u6cf5\u67f4\u6cb9 \u624b\u52a8 \u8c6a\u534e\u578b \u8d85\u957f\u7248","price":"7.08","year":"2010","max_year":"2013","min_year":"2009"},{"key":"8149","brand_id":"45","series_id":"544","value":"2010\u6b3e GA1020CRE3A\/B3BZ-37 \u6807\u51c6\u578b","nameL":"2010\u6b3e \u8d22\u8fd0100 GA1020CRE3A\/B3BZ-37 \u6807\u51c6\u578b","price":"7.38","year":"2010","max_year":"2013","min_year":"2009"},{"key":"8150","brand_id":"45","series_id":"544","value":"2010\u6b3e \u5927\u8d22\u8fd0 GA1020LCRE3A\/B3BZT-37 \u6807\u51c6\u578b","nameL":"2010\u6b3e \u8d22\u8fd0100 \u5927\u8d22\u8fd0 GA1020LCRE3A\/B3BZT-37 \u6807\u51c6\u578b","price":"7.48","year":"2010","max_year":"2013","min_year":"2009"},{"key":"22315","brand_id":"45","series_id":"544","value":"2009\u6b3e 2.2T\u83b1\u52a8\u67f4\u6cb9\u7ecf\u6d4e\u578b\u77ed\u8d27\u7bb1","nameL":"2009\u6b3e \u8d22\u8fd0100 2.2T\u83b1\u52a8\u67f4\u6cb9\u7ecf\u6d4e\u578b\u77ed\u8d27\u7bb1","price":"5.39","year":"2009","max_year":"2011","min_year":"2009"},{"key":"22316","brand_id":"45","series_id":"544","value":"2009\u6b3e 2.2T\u83b1\u52a8\u67f4\u6cb9\u7ecf\u6d4e\u578b\u4e2d\u8d27\u7bb1","nameL":"2009\u6b3e \u8d22\u8fd0100 2.2T\u83b1\u52a8\u67f4\u6cb9\u7ecf\u6d4e\u578b\u4e2d\u8d27\u7bb1","price":"5.39","year":"2009","max_year":"2011","min_year":"2009"},{"key":"22317","brand_id":"45","series_id":"544","value":"2009\u6b3e 2.2T\u83b1\u52a8\u67f4\u6cb9\u7ecf\u6d4e\u578b\u957f\u8d27\u7bb1","nameL":"2009\u6b3e \u8d22\u8fd0100 2.2T\u83b1\u52a8\u67f4\u6cb9\u7ecf\u6d4e\u578b\u957f\u8d27\u7bb1","price":"5.39","year":"2009","max_year":"2011","min_year":"2009"},{"key":"22318","brand_id":"45","series_id":"544","value":"2009\u6b3e 2.2T\u83b1\u52a8\u67f4\u6cb9\u6807\u51c6\u578b\u77ed\u8d27\u7bb1","nameL":"2009\u6b3e \u8d22\u8fd0100 2.2T\u83b1\u52a8\u67f4\u6cb9\u6807\u51c6\u578b\u77ed\u8d27\u7bb1","price":"6.03","year":"2009","max_year":"2011","min_year":"2009"},{"key":"22319","brand_id":"45","series_id":"544","value":"2009\u6b3e 2.2T\u83b1\u52a8\u67f4\u6cb9\u6807\u51c6\u578b\u4e2d\u8d27\u7bb1","nameL":"2009\u6b3e \u8d22\u8fd0100 2.2T\u83b1\u52a8\u67f4\u6cb9\u6807\u51c6\u578b\u4e2d\u8d27\u7bb1","price":"6.03","year":"2009","max_year":"2011","min_year":"2009"},{"key":"22320","brand_id":"45","series_id":"544","value":"2009\u6b3e 2.2T\u83b1\u52a8\u67f4\u6cb9\u6807\u51c6\u578b\u957f\u8d27\u7bb1","nameL":"2009\u6b3e \u8d22\u8fd0100 2.2T\u83b1\u52a8\u67f4\u6cb9\u6807\u51c6\u578b\u957f\u8d27\u7bb1","price":"6.03","year":"2009","max_year":"2011","min_year":"2009"},{"key":"22312","brand_id":"45","series_id":"544","value":"2009\u6b3e 2.8T-VE\u6cf5\u67f4\u6cb9\u8c6a\u534e\u578b\u77ed\u8d27\u7bb1","nameL":"2009\u6b3e \u8d22\u8fd0100 2.8T-VE\u6cf5\u67f4\u6cb9\u8c6a\u534e\u578b\u77ed\u8d27\u7bb1","price":"6.58","year":"2009","max_year":"2011","min_year":"2009"},{"key":"22313","brand_id":"45","series_id":"544","value":"2009\u6b3e 2.8T-VE\u6cf5\u67f4\u6cb9\u8c6a\u534e\u578b\u4e2d\u8d27\u7bb1","nameL":"2009\u6b3e \u8d22\u8fd0100 2.8T-VE\u6cf5\u67f4\u6cb9\u8c6a\u534e\u578b\u4e2d\u8d27\u7bb1","price":"6.58","year":"2009","max_year":"2011","min_year":"2009"},{"key":"22314","brand_id":"45","series_id":"544","value":"2009\u6b3e 2.8T-VE\u6cf5\u67f4\u6cb9\u8c6a\u534e\u578b\u957f\u8d27\u7bb1","nameL":"2009\u6b3e \u8d22\u8fd0100 2.8T-VE\u6cf5\u67f4\u6cb9\u8c6a\u534e\u578b\u957f\u8d27\u7bb1","price":"6.58","year":"2009","max_year":"2011","min_year":"2009"},{"key":"22321","brand_id":"45","series_id":"544","value":"2009\u6b3e 2.2L\u6c7d\u6cb9\u7ecf\u6d4e\u578b\u77ed\u8d27\u7bb1","nameL":"2009\u6b3e \u8d22\u8fd0100 2.2L\u6c7d\u6cb9\u7ecf\u6d4e\u578b\u77ed\u8d27\u7bb1","price":"5.69","year":"2009","max_year":"2011","min_year":"2009"},{"key":"22322","brand_id":"45","series_id":"544","value":"2009\u6b3e 2.2L\u6c7d\u6cb9\u7ecf\u6d4e\u578b\u4e2d\u8d27\u7bb1","nameL":"2009\u6b3e \u8d22\u8fd0100 2.2L\u6c7d\u6cb9\u7ecf\u6d4e\u578b\u4e2d\u8d27\u7bb1","price":"5.69","year":"2009","max_year":"2011","min_year":"2009"},{"key":"22323","brand_id":"45","series_id":"544","value":"2009\u6b3e 2.2L\u6c7d\u6cb9\u7ecf\u6d4e\u578b\u957f\u8d27\u7bb1","nameL":"2009\u6b3e \u8d22\u8fd0100 2.2L\u6c7d\u6cb9\u7ecf\u6d4e\u578b\u957f\u8d27\u7bb1","price":"5.69","year":"2009","max_year":"2011","min_year":"2009"},{"key":"22324","brand_id":"45","series_id":"544","value":"2009\u6b3e 2.2L\u6c7d\u6cb9\u6807\u51c6\u578b\u77ed\u8d27\u7bb1","nameL":"2009\u6b3e \u8d22\u8fd0100 2.2L\u6c7d\u6cb9\u6807\u51c6\u578b\u77ed\u8d27\u7bb1","price":"6.28","year":"2009","max_year":"2011","min_year":"2009"},{"key":"22325","brand_id":"45","series_id":"544","value":"2009\u6b3e 2.2L\u6c7d\u6cb9\u6807\u51c6\u578b\u4e2d\u8d27\u7bb1","nameL":"2009\u6b3e \u8d22\u8fd0100 2.2L\u6c7d\u6cb9\u6807\u51c6\u578b\u4e2d\u8d27\u7bb1","price":"6.28","year":"2009","max_year":"2011","min_year":"2009"},{"key":"22326","brand_id":"45","series_id":"544","value":"2009\u6b3e 2.2L\u6c7d\u6cb9\u6807\u51c6\u578b\u957f\u8d27\u7bb1","nameL":"2009\u6b3e \u8d22\u8fd0100 2.2L\u6c7d\u6cb9\u6807\u51c6\u578b\u957f\u8d27\u7bb1","price":"6.28","year":"2009","max_year":"2011","min_year":"2009"},{"key":"8151","brand_id":"45","series_id":"544","value":"2009\u6b3e GA1020E3A\/B3XZ-31 \u6807\u51c6\u578b","nameL":"2009\u6b3e \u8d22\u8fd0100 GA1020E3A\/B3XZ-31 \u6807\u51c6\u578b","price":"6.43","year":"2009","max_year":"2011","min_year":"2008"},{"key":"8152","brand_id":"45","series_id":"544","value":"2009\u6b3e GA1020E3\/B3XZ-30 \u6807\u51c6\u578b","nameL":"2009\u6b3e \u8d22\u8fd0100 GA1020E3\/B3XZ-30 \u6807\u51c6\u578b","price":"6.48","year":"2009","max_year":"2011","min_year":"2008"},{"key":"8153","brand_id":"45","series_id":"544","value":"2009\u6b3e GA1020CRE3A\/B3XZ-35 \u6807\u51c6\u578b","nameL":"2009\u6b3e \u8d22\u8fd0100 GA1020CRE3A\/B3XZ-35 \u6807\u51c6\u578b","price":"7.18","year":"2009","max_year":"2011","min_year":"2008"}]