[{"key":"11551","brand_id":"69","series_id":"747","value":"2013\u6b3e 2.0L \u624b\u52a8 \u6c7d\u6cb9\u8f66\u578b-\u77ed\u9014\u5ba2\u8fd0\/\u5355\u4f4d\u901a\u52e4","nameL":"2013\u6b3e \u91d1\u9f99\u91d1\u5a01 2.0L \u624b\u52a8 \u6c7d\u6cb9\u8f66\u578b-\u77ed\u9014\u5ba2\u8fd0\/\u5355\u4f4d\u901a\u52e4","price":"7.48","year":"2013","max_year":"2016","min_year":"2012"},{"key":"11552","brand_id":"69","series_id":"747","value":"2013\u6b3e 2.0L \u624b\u52a8 \u6c7d\u6cb9\u8f66\u578b-\u5ba2\u8d27\u4e24\u7528","nameL":"2013\u6b3e \u91d1\u9f99\u91d1\u5a01 2.0L \u624b\u52a8 \u6c7d\u6cb9\u8f66\u578b-\u5ba2\u8d27\u4e24\u7528","price":"7.48","year":"2013","max_year":"2016","min_year":"2012"},{"key":"11553","brand_id":"69","series_id":"747","value":"2013\u6b3e 2.0L \u624b\u52a8 VVT \u6c7d\u6cb9\u8f66\u578b-\u77ed\u9014\u5ba2\u8fd0\/\u5355\u4f4d\u901a\u52e4","nameL":"2013\u6b3e \u91d1\u9f99\u91d1\u5a01 2.0L \u624b\u52a8 VVT \u6c7d\u6cb9\u8f66\u578b-\u77ed\u9014\u5ba2\u8fd0\/\u5355\u4f4d\u901a\u52e4","price":"9.48","year":"2013","max_year":"2016","min_year":"2012"},{"key":"11554","brand_id":"69","series_id":"747","value":"2013\u6b3e 2.0L \u624b\u52a8 VVT \u6c7d\u6cb9\u8f66\u578b-\u5ba2\u8d27\u4e24\u7528","nameL":"2013\u6b3e \u91d1\u9f99\u91d1\u5a01 2.0L \u624b\u52a8 VVT \u6c7d\u6cb9\u8f66\u578b-\u5ba2\u8d27\u4e24\u7528","price":"9.48","year":"2013","max_year":"2016","min_year":"2012"},{"key":"11555","brand_id":"69","series_id":"747","value":"2013\u6b3e 2.2L \u624b\u52a8 \u6c7d\u6cb9\u8f66\u578b-\u5ba2\u8d27\u4e24\u7528","nameL":"2013\u6b3e \u91d1\u9f99\u91d1\u5a01 2.2L \u624b\u52a8 \u6c7d\u6cb9\u8f66\u578b-\u5ba2\u8d27\u4e24\u7528","price":"7.68","year":"2013","max_year":"2016","min_year":"2012"},{"key":"11556","brand_id":"69","series_id":"747","value":"2013\u6b3e 2.2L \u624b\u52a8 CNG \u6c7d\u6cb9\u8f66\u578b-\u5ba2\u8d27\u4e24\u7528","nameL":"2013\u6b3e \u91d1\u9f99\u91d1\u5a01 2.2L \u624b\u52a8 CNG \u6c7d\u6cb9\u8f66\u578b-\u5ba2\u8d27\u4e24\u7528","price":"8.98","year":"2013","max_year":"2016","min_year":"2012"},{"key":"11557","brand_id":"69","series_id":"747","value":"2013\u6b3e 2.2L \u624b\u52a8 CNG \u6c7d\u6cb9\u8f66\u578b-\u77ed\u9014\u5ba2\u8fd0\/\u5355\u4f4d\u901a\u52e4","nameL":"2013\u6b3e \u91d1\u9f99\u91d1\u5a01 2.2L \u624b\u52a8 CNG \u6c7d\u6cb9\u8f66\u578b-\u77ed\u9014\u5ba2\u8fd0\/\u5355\u4f4d\u901a\u52e4","price":"8.98","year":"2013","max_year":"2016","min_year":"2012"},{"key":"11558","brand_id":"69","series_id":"747","value":"2013\u6b3e 2.4L \u624b\u52a8 \u6c7d\u6cb9\u8f66\u578b-\u5546\u52a1\u63a5\u5f85\/\u5355\u4f4d\u901a\u52e4","nameL":"2013\u6b3e \u91d1\u9f99\u91d1\u5a01 2.4L \u624b\u52a8 \u6c7d\u6cb9\u8f66\u578b-\u5546\u52a1\u63a5\u5f85\/\u5355\u4f4d\u901a\u52e4","price":"8.98","year":"2013","max_year":"2016","min_year":"2012"},{"key":"11559","brand_id":"69","series_id":"747","value":"2013\u6b3e 2.4L \u624b\u52a8 \u6c7d\u6cb9\u8f66\u578b-\u5546\u52a1\u63a5\u5f85","nameL":"2013\u6b3e \u91d1\u9f99\u91d1\u5a01 2.4L \u624b\u52a8 \u6c7d\u6cb9\u8f66\u578b-\u5546\u52a1\u63a5\u5f85","price":"8.98","year":"2013","max_year":"2016","min_year":"2012"},{"key":"11560","brand_id":"69","series_id":"747","value":"2013\u6b3e 2.5L \u624b\u52a8 \u67f4\u6cb9\u8f66\u578b-\u77ed\u9014\u5ba2\u8fd0\/\u5355\u4f4d\u901a\u52e4","nameL":"2013\u6b3e \u91d1\u9f99\u91d1\u5a01 2.5L \u624b\u52a8 \u67f4\u6cb9\u8f66\u578b-\u77ed\u9014\u5ba2\u8fd0\/\u5355\u4f4d\u901a\u52e4","price":"10.38","year":"2013","max_year":"2016","min_year":"2012"},{"key":"11561","brand_id":"69","series_id":"747","value":"2013\u6b3e 2.5L \u624b\u52a8 \u67f4\u6cb9\u8f66\u578b-\u5ba2\u8d27\u4e24\u7528","nameL":"2013\u6b3e \u91d1\u9f99\u91d1\u5a01 2.5L \u624b\u52a8 \u67f4\u6cb9\u8f66\u578b-\u5ba2\u8d27\u4e24\u7528","price":"10.38","year":"2013","max_year":"2016","min_year":"2012"}]