[{"key":"6","value":"\u592a\u539f","sld":"ty"},{"key":"36","value":"\u5927\u540c","sld":"datong"},{"key":"64","value":"\u9633\u6cc9","sld":"yangquan"},{"key":"92","value":"\u957f\u6cbb","sld":"changzhi"},{"key":"120","value":"\u664b\u57ce","sld":"jincheng"},{"key":"148","value":"\u6714\u5dde","sld":"shuozhou"},{"key":"175","value":"\u664b\u4e2d","sld":"jinzhong"},{"key":"202","value":"\u8fd0\u57ce","sld":"yuncheng"},{"key":"228","value":"\u5ffb\u5dde","sld":"xinzhou"},{"key":"253","value":"\u4e34\u6c7e","sld":"linfen"},{"key":"275","value":"\u5415\u6881","sld":"lvliang"}]